{
  "BTC-USD": "STRONG_BUY",
  "ETH-USD": "STRONG_BUY",
  "BNB-USD": "STRONG_BUY",
  "XRP-USD": "STRONG_BUY",
  "SOL-USD": "STRONG_BUY",
  "HYPE-USD": "BUY",
  "XLM-USD": "NEUTRAL",
  "DOGE-USD": "STRONG_BUY",
  "ZEC-USD": "BUY",
  "ADA-USD": "STRONG_BUY",
  "LINK-USD": "STRONG_BUY",
  "HBAR-USD": "NEUTRAL",
  "BCH-USD": "STRONG_BUY",
  "TON-USD": "STRONG_BUY",
  "USD1-USD": "STRONG_BUY",
  "LTC-USD": "SELL",
  "AVAX-USD": "BUY",
  "SUI-USD": "BUY",
  "SHIB-USD": "STRONG_BUY",
  "NEAR-USD": "SELL",
  "CRO-USD": "SELL",
  "TAO-USD": "STRONG_BUY",
  "UNI-USD": "STRONG_BUY",
  "DOT-USD": "NEUTRAL",
  "PAXG-USD": "SELL",
  "WLFI-USD": "BUY",
  "ASTER-USD": "STRONG_BUY",
  "ONDO-USD": "SELL"
}