{
  "HBAR-USD": {
    "score": -3,
    "wins": 0,
    "losses": 3
  },
  "XLM-USD": {
    "score": 3,
    "wins": 3,
    "losses": 0
  },
  "SHIB-USD": {
    "score": 3,
    "wins": 3,
    "losses": 0
  },
  "LINK-USD": {
    "score": -3,
    "wins": 0,
    "losses": 6
  },
  "TAO-USD": {
    "score": -3,
    "wins": 0,
    "losses": 3
  },
  "BTC-USD": {
    "score": -3,
    "wins": 0,
    "losses": 6
  },
  "ETH-USD": {
    "score": -3,
    "wins": 0,
    "losses": 6
  },
  "BNB-USD": {
    "score": -3,
    "wins": 0,
    "losses": 6
  },
  "TON-USD": {
    "score": -3,
    "wins": 0,
    "losses": 3
  },
  "LTC-USD": {
    "score": -3,
    "wins": 0,
    "losses": 3
  },
  "XRP-USD": {
    "score": 3,
    "wins": 6,
    "losses": 0
  },
  "ZEC-USD": {
    "score": 0,
    "wins": 3,
    "losses": 3
  },
  "AVAX-USD": {
    "score": 1,
    "wins": 1,
    "losses": 0
  },
  "DOT-USD": {
    "score": 1,
    "wins": 1,
    "losses": 0
  },
  "ASTER-USD": {
    "score": 1,
    "wins": 1,
    "losses": 0
  },
  "HBAR-USD:LONG": {
    "score": -3,
    "wins": 0,
    "losses": 330
  },
  "XLM-USD:LONG": {
    "score": 3,
    "wins": 344,
    "losses": 0
  },
  "SHIB-USD:LONG": {
    "score": 3,
    "wins": 367,
    "losses": 0
  },
  "LINK-USD:LONG": {
    "score": -3,
    "wins": 0,
    "losses": 900
  },
  "TAO-USD:LONG": {
    "score": -3,
    "wins": 0,
    "losses": 450
  },
  "BTC-USD:LONG": {
    "score": -3,
    "wins": 0,
    "losses": 1350
  },
  "ETH-USD:LONG": {
    "score": -3,
    "wins": 0,
    "losses": 900
  },
  "BNB-USD:LONG": {
    "score": -3,
    "wins": 0,
    "losses": 900
  },
  "TON-USD:LONG": {
    "score": -3,
    "wins": 0,
    "losses": 450
  },
  "LTC-USD:LONG": {
    "score": -3,
    "wins": 0,
    "losses": 450
  },
  "XRP-USD:LONG": {
    "score": 3,
    "wins": 900,
    "losses": 0
  },
  "ZEC-USD:LONG": {
    "score": 0,
    "wins": 450,
    "losses": 450
  },
  "AVAX-USD:LONG": {
    "score": 3,
    "wins": 450,
    "losses": 0
  },
  "DOT-USD:LONG": {
    "score": 3,
    "wins": 450,
    "losses": 0
  },
  "ASTER-USD:LONG": {
    "score": 3,
    "wins": 450,
    "losses": 0
  },
  "SOL-USD:LONG": {
    "score": -3,
    "wins": 0,
    "losses": 450
  },
  "OP-USD:LONG": {
    "score": -3,
    "wins": 0,
    "losses": 449
  },
  "NEAR-USD:SHORT": {
    "score": 1,
    "wins": 1396,
    "losses": 401
  },
  "FET-USD:SHORT": {
    "score": -3,
    "wins": 0,
    "losses": 714
  },
  "INJ-USD:SHORT": {
    "score": -3,
    "wins": 0,
    "losses": 666
  },
  "FIL-USD:LONG": {
    "score": -3,
    "wins": 0,
    "losses": 358
  },
  "ETH-USD:SHORT": {
    "score": 3,
    "wins": 317,
    "losses": 0
  },
  "BTC-USD:SHORT": {
    "score": 3,
    "wins": 314,
    "losses": 0
  },
  "SHIB-USD:SHORT": {
    "score": 3,
    "wins": 314,
    "losses": 0
  },
  "FIL-USD:SHORT": {
    "score": 2,
    "wins": 576,
    "losses": 175
  },
  "SEI-USD:SHORT": {
    "score": -3,
    "wins": 0,
    "losses": 302
  },
  "BCH-USD:SHORT": {
    "score": 2,
    "wins": 287,
    "losses": 216
  },
  "DOGE-USD:SHORT": {
    "score": -3,
    "wins": 0,
    "losses": 260
  },
  "GRT-USD:LONG": {
    "score": -3,
    "wins": 0,
    "losses": 224
  },
  "INJ-USD:LONG": {
    "score": 3,
    "wins": 211,
    "losses": 0
  },
  "ICP-USD:LONG": {
    "score": -3,
    "wins": 0,
    "losses": 188
  },
  "UNI-USD:LONG": {
    "score": -3,
    "wins": 0,
    "losses": 179
  },
  "OP-USD:SHORT": {
    "score": 0,
    "wins": 0,
    "losses": 0
  },
  "XRP-USD:SHORT": {
    "score": -3,
    "wins": 0,
    "losses": 138
  },
  "GRT-USD:SHORT": {
    "score": -3,
    "wins": 0,
    "losses": 83
  }
}