{
  "HBAR-USD": {
    "score": -3,
    "wins": 0,
    "losses": 3
  },
  "XLM-USD": {
    "score": 3,
    "wins": 3,
    "losses": 0
  },
  "SHIB-USD": {
    "score": 3,
    "wins": 3,
    "losses": 0
  },
  "LINK-USD": {
    "score": -3,
    "wins": 0,
    "losses": 6
  },
  "TAO-USD": {
    "score": -3,
    "wins": 0,
    "losses": 3
  },
  "BTC-USD": {
    "score": -3,
    "wins": 0,
    "losses": 6
  },
  "ETH-USD": {
    "score": -3,
    "wins": 0,
    "losses": 6
  },
  "BNB-USD": {
    "score": -3,
    "wins": 0,
    "losses": 6
  },
  "TON-USD": {
    "score": -3,
    "wins": 0,
    "losses": 3
  },
  "LTC-USD": {
    "score": -3,
    "wins": 0,
    "losses": 3
  },
  "XRP-USD": {
    "score": 3,
    "wins": 6,
    "losses": 0
  },
  "ZEC-USD": {
    "score": 0,
    "wins": 3,
    "losses": 3
  },
  "AVAX-USD": {
    "score": 1,
    "wins": 1,
    "losses": 0
  },
  "DOT-USD": {
    "score": 1,
    "wins": 1,
    "losses": 0
  },
  "ASTER-USD": {
    "score": 1,
    "wins": 1,
    "losses": 0
  },
  "HBAR-USD:LONG": {
    "score": -3,
    "wins": 0,
    "losses": 292
  },
  "XLM-USD:LONG": {
    "score": 3,
    "wins": 292,
    "losses": 0
  },
  "SHIB-USD:LONG": {
    "score": 3,
    "wins": 292,
    "losses": 0
  },
  "LINK-USD:LONG": {
    "score": -3,
    "wins": 0,
    "losses": 584
  },
  "TAO-USD:LONG": {
    "score": -3,
    "wins": 0,
    "losses": 292
  },
  "BTC-USD:LONG": {
    "score": -3,
    "wins": 0,
    "losses": 876
  },
  "ETH-USD:LONG": {
    "score": -3,
    "wins": 0,
    "losses": 584
  },
  "BNB-USD:LONG": {
    "score": -3,
    "wins": 0,
    "losses": 584
  },
  "TON-USD:LONG": {
    "score": -3,
    "wins": 0,
    "losses": 292
  },
  "LTC-USD:LONG": {
    "score": -3,
    "wins": 0,
    "losses": 292
  },
  "XRP-USD:LONG": {
    "score": 3,
    "wins": 584,
    "losses": 0
  },
  "ZEC-USD:LONG": {
    "score": 0,
    "wins": 292,
    "losses": 292
  },
  "AVAX-USD:LONG": {
    "score": 3,
    "wins": 292,
    "losses": 0
  },
  "DOT-USD:LONG": {
    "score": 3,
    "wins": 292,
    "losses": 0
  },
  "ASTER-USD:LONG": {
    "score": 3,
    "wins": 292,
    "losses": 0
  },
  "SOL-USD:LONG": {
    "score": -3,
    "wins": 0,
    "losses": 292
  },
  "OP-USD:LONG": {
    "score": -3,
    "wins": 0,
    "losses": 291
  },
  "NEAR-USD:SHORT": {
    "score": 2,
    "wins": 799,
    "losses": 17
  },
  "FET-USD:SHORT": {
    "score": -3,
    "wins": 0,
    "losses": 398
  },
  "INJ-USD:SHORT": {
    "score": -3,
    "wins": 0,
    "losses": 350
  },
  "FIL-USD:LONG": {
    "score": -3,
    "wins": 0,
    "losses": 200
  },
  "ETH-USD:SHORT": {
    "score": 3,
    "wins": 159,
    "losses": 0
  },
  "BTC-USD:SHORT": {
    "score": 3,
    "wins": 156,
    "losses": 0
  },
  "SHIB-USD:SHORT": {
    "score": 3,
    "wins": 156,
    "losses": 0
  },
  "FIL-USD:SHORT": {
    "score": 2,
    "wins": 260,
    "losses": 17
  },
  "SEI-USD:SHORT": {
    "score": -3,
    "wins": 0,
    "losses": 144
  },
  "BCH-USD:SHORT": {
    "score": 2,
    "wins": 129,
    "losses": 58
  },
  "DOGE-USD:SHORT": {
    "score": -3,
    "wins": 0,
    "losses": 102
  },
  "GRT-USD:LONG": {
    "score": -3,
    "wins": 0,
    "losses": 66
  },
  "INJ-USD:LONG": {
    "score": 3,
    "wins": 53,
    "losses": 0
  },
  "ICP-USD:LONG": {
    "score": -3,
    "wins": 0,
    "losses": 30
  },
  "UNI-USD:LONG": {
    "score": -3,
    "wins": 0,
    "losses": 21
  },
  "OP-USD:SHORT": {
    "score": 0,
    "wins": 0,
    "losses": 0
  }
}