{
  "HBAR-USD": {
    "score": -3,
    "wins": 0,
    "losses": 3
  },
  "XLM-USD": {
    "score": 3,
    "wins": 3,
    "losses": 0
  },
  "SHIB-USD": {
    "score": 3,
    "wins": 3,
    "losses": 0
  },
  "LINK-USD": {
    "score": -3,
    "wins": 0,
    "losses": 6
  },
  "TAO-USD": {
    "score": -3,
    "wins": 0,
    "losses": 3
  },
  "BTC-USD": {
    "score": -3,
    "wins": 0,
    "losses": 6
  },
  "ETH-USD": {
    "score": -3,
    "wins": 0,
    "losses": 6
  },
  "BNB-USD": {
    "score": -3,
    "wins": 0,
    "losses": 6
  },
  "TON-USD": {
    "score": -3,
    "wins": 0,
    "losses": 3
  },
  "LTC-USD": {
    "score": -3,
    "wins": 0,
    "losses": 3
  },
  "XRP-USD": {
    "score": 3,
    "wins": 6,
    "losses": 0
  },
  "ZEC-USD": {
    "score": 0,
    "wins": 3,
    "losses": 3
  },
  "AVAX-USD": {
    "score": 1,
    "wins": 1,
    "losses": 0
  },
  "DOT-USD": {
    "score": 1,
    "wins": 1,
    "losses": 0
  },
  "ASTER-USD": {
    "score": 1,
    "wins": 1,
    "losses": 0
  },
  "HBAR-USD:LONG": {
    "score": -3,
    "wins": 0,
    "losses": 140
  },
  "XLM-USD:LONG": {
    "score": 3,
    "wins": 140,
    "losses": 0
  },
  "SHIB-USD:LONG": {
    "score": 3,
    "wins": 140,
    "losses": 0
  },
  "LINK-USD:LONG": {
    "score": -3,
    "wins": 0,
    "losses": 280
  },
  "TAO-USD:LONG": {
    "score": -3,
    "wins": 0,
    "losses": 140
  },
  "BTC-USD:LONG": {
    "score": -3,
    "wins": 0,
    "losses": 420
  },
  "ETH-USD:LONG": {
    "score": -3,
    "wins": 0,
    "losses": 280
  },
  "BNB-USD:LONG": {
    "score": -3,
    "wins": 0,
    "losses": 280
  },
  "TON-USD:LONG": {
    "score": -3,
    "wins": 0,
    "losses": 140
  },
  "LTC-USD:LONG": {
    "score": -3,
    "wins": 0,
    "losses": 140
  },
  "XRP-USD:LONG": {
    "score": 3,
    "wins": 280,
    "losses": 0
  },
  "ZEC-USD:LONG": {
    "score": 0,
    "wins": 140,
    "losses": 140
  },
  "AVAX-USD:LONG": {
    "score": 3,
    "wins": 140,
    "losses": 0
  },
  "DOT-USD:LONG": {
    "score": 3,
    "wins": 140,
    "losses": 0
  },
  "ASTER-USD:LONG": {
    "score": 3,
    "wins": 140,
    "losses": 0
  },
  "SOL-USD:LONG": {
    "score": -3,
    "wins": 0,
    "losses": 140
  },
  "OP-USD:LONG": {
    "score": -3,
    "wins": 0,
    "losses": 139
  },
  "NEAR-USD:SHORT": {
    "score": 3,
    "wins": 343,
    "losses": 0
  },
  "FET-USD:SHORT": {
    "score": -3,
    "wins": 0,
    "losses": 94
  },
  "INJ-USD:SHORT": {
    "score": -3,
    "wins": 0,
    "losses": 53
  },
  "FIL-USD:LONG": {
    "score": -3,
    "wins": 0,
    "losses": 48
  },
  "ETH-USD:SHORT": {
    "score": 3,
    "wins": 7,
    "losses": 0
  },
  "BTC-USD:SHORT": {
    "score": 3,
    "wins": 4,
    "losses": 0
  },
  "SHIB-USD:SHORT": {
    "score": 3,
    "wins": 4,
    "losses": 0
  }
}