{
  "HBAR-USD": {
    "score": -3,
    "wins": 0,
    "losses": 3
  },
  "XLM-USD": {
    "score": 3,
    "wins": 3,
    "losses": 0
  },
  "SHIB-USD": {
    "score": 3,
    "wins": 3,
    "losses": 0
  },
  "LINK-USD": {
    "score": -3,
    "wins": 0,
    "losses": 6
  },
  "TAO-USD": {
    "score": -3,
    "wins": 0,
    "losses": 3
  },
  "BTC-USD": {
    "score": -3,
    "wins": 0,
    "losses": 6
  },
  "ETH-USD": {
    "score": -3,
    "wins": 0,
    "losses": 6
  },
  "BNB-USD": {
    "score": -3,
    "wins": 0,
    "losses": 6
  },
  "TON-USD": {
    "score": -3,
    "wins": 0,
    "losses": 3
  },
  "LTC-USD": {
    "score": -3,
    "wins": 0,
    "losses": 3
  },
  "XRP-USD": {
    "score": 3,
    "wins": 6,
    "losses": 0
  },
  "ZEC-USD": {
    "score": 0,
    "wins": 3,
    "losses": 3
  },
  "AVAX-USD": {
    "score": 1,
    "wins": 1,
    "losses": 0
  },
  "DOT-USD": {
    "score": 1,
    "wins": 1,
    "losses": 0
  },
  "ASTER-USD": {
    "score": 1,
    "wins": 1,
    "losses": 0
  },
  "HBAR-USD:LONG": {
    "score": -3,
    "wins": 0,
    "losses": 330
  },
  "XLM-USD:LONG": {
    "score": 3,
    "wins": 344,
    "losses": 0
  },
  "SHIB-USD:LONG": {
    "score": 3,
    "wins": 365,
    "losses": 0
  },
  "LINK-USD:LONG": {
    "score": -3,
    "wins": 0,
    "losses": 730
  },
  "TAO-USD:LONG": {
    "score": -3,
    "wins": 0,
    "losses": 365
  },
  "BTC-USD:LONG": {
    "score": -3,
    "wins": 0,
    "losses": 1095
  },
  "ETH-USD:LONG": {
    "score": -3,
    "wins": 0,
    "losses": 730
  },
  "BNB-USD:LONG": {
    "score": -3,
    "wins": 0,
    "losses": 730
  },
  "TON-USD:LONG": {
    "score": -3,
    "wins": 0,
    "losses": 365
  },
  "LTC-USD:LONG": {
    "score": -3,
    "wins": 0,
    "losses": 365
  },
  "XRP-USD:LONG": {
    "score": 3,
    "wins": 730,
    "losses": 0
  },
  "ZEC-USD:LONG": {
    "score": 0,
    "wins": 365,
    "losses": 365
  },
  "AVAX-USD:LONG": {
    "score": 3,
    "wins": 365,
    "losses": 0
  },
  "DOT-USD:LONG": {
    "score": 3,
    "wins": 365,
    "losses": 0
  },
  "ASTER-USD:LONG": {
    "score": 3,
    "wins": 365,
    "losses": 0
  },
  "SOL-USD:LONG": {
    "score": -3,
    "wins": 0,
    "losses": 365
  },
  "OP-USD:LONG": {
    "score": -3,
    "wins": 0,
    "losses": 364
  },
  "NEAR-USD:SHORT": {
    "score": 1,
    "wins": 1056,
    "losses": 146
  },
  "FET-USD:SHORT": {
    "score": -3,
    "wins": 0,
    "losses": 544
  },
  "INJ-USD:SHORT": {
    "score": -3,
    "wins": 0,
    "losses": 496
  },
  "FIL-USD:LONG": {
    "score": -3,
    "wins": 0,
    "losses": 273
  },
  "ETH-USD:SHORT": {
    "score": 3,
    "wins": 232,
    "losses": 0
  },
  "BTC-USD:SHORT": {
    "score": 3,
    "wins": 229,
    "losses": 0
  },
  "SHIB-USD:SHORT": {
    "score": 3,
    "wins": 229,
    "losses": 0
  },
  "FIL-USD:SHORT": {
    "score": 2,
    "wins": 406,
    "losses": 90
  },
  "SEI-USD:SHORT": {
    "score": -3,
    "wins": 0,
    "losses": 217
  },
  "BCH-USD:SHORT": {
    "score": 2,
    "wins": 202,
    "losses": 131
  },
  "DOGE-USD:SHORT": {
    "score": -3,
    "wins": 0,
    "losses": 175
  },
  "GRT-USD:LONG": {
    "score": -3,
    "wins": 0,
    "losses": 139
  },
  "INJ-USD:LONG": {
    "score": 3,
    "wins": 126,
    "losses": 0
  },
  "ICP-USD:LONG": {
    "score": -3,
    "wins": 0,
    "losses": 103
  },
  "UNI-USD:LONG": {
    "score": -3,
    "wins": 0,
    "losses": 94
  },
  "OP-USD:SHORT": {
    "score": 0,
    "wins": 0,
    "losses": 0
  },
  "XRP-USD:SHORT": {
    "score": -3,
    "wins": 0,
    "losses": 53
  }
}