{
  "last_run": "2026-05-28T19:22:21.351397",
  "status": "running",
  "mode": "paper_long_short",
  "btc_trend": {
    "bullish": true,
    "bearish": false,
    "bull_score": 65,
    "bear_score": 20,
    "reason": "BTC above EMA20; BTC above EMA50; BTC EMA20 < EMA50"
  },
  "daily_realized_pnl": 0.45364082328279093,
  "daily_trade_count": 16,
  "max_trades_per_day": 14,
  "daily_loss_limit": 3.0,
  "open_positions": 2,
  "cash": 40.67607033062993,
  "total_value": 49.59884374310084,
  "top_signals": [
    {
      "pair": "SEI-USD",
      "price": 0.07027,
      "long_score": 80,
      "short_score": 17.0,
      "score": 80,
      "signal": "BUY",
      "rsi14": 65.76,
      "macd_hist": 3.2e-05,
      "atr_pct": 1.11,
      "volume_ok": false,
      "long_reason": "price > EMA20; price > EMA50; bull EMA alignment; RSI healthy; MACD positive; BTC bullish",
      "short_reason": "RSI fade zone; MACD weakening",
      "reason": "price > EMA20; price > EMA50; bull EMA alignment; RSI healthy; MACD positive; BTC bullish"
    },
    {
      "pair": "MATIC-USD",
      "price": 0.1995,
      "long_score": 80,
      "short_score": 18,
      "score": 80,
      "signal": "BUY",
      "rsi14": 65.19,
      "macd_hist": 0.000748,
      "atr_pct": 1.17,
      "volume_ok": true,
      "long_reason": "price > EMA20; price > EMA50; RSI healthy; MACD positive; MACD improving; volume active; BTC bullish",
      "short_reason": "RSI fade zone; volume active",
      "reason": "price > EMA20; price > EMA50; RSI healthy; MACD positive; MACD improving; volume active; BTC bullish"
    },
    {
      "pair": "SHIB-USD",
      "price": 5.36e-06,
      "long_score": 75.0,
      "short_score": 15.0,
      "score": 75.0,
      "signal": "BUY",
      "rsi14": 63.16,
      "macd_hist": 0.0,
      "atr_pct": 0.36,
      "volume_ok": false,
      "long_reason": "price > EMA20; price > EMA50; bull EMA alignment; RSI healthy; MACD positive; BTC bullish",
      "short_reason": "RSI fade zone; MACD weakening",
      "reason": "price > EMA20; price > EMA50; bull EMA alignment; RSI healthy; MACD positive; BTC bullish"
    },
    {
      "pair": "AVAX-USD",
      "price": 8.93,
      "long_score": 71.0,
      "short_score": 32,
      "score": 71.0,
      "signal": "HOLD",
      "rsi14": 63.64,
      "macd_hist": -0.001813,
      "atr_pct": 0.48,
      "volume_ok": true,
      "long_reason": "price > EMA20; price > EMA50; bull EMA alignment; RSI healthy; volume active; BTC bullish",
      "short_reason": "RSI fade zone; MACD negative; MACD weakening; volume active",
      "reason": "RSI fade zone; MACD negative; MACD weakening; volume active"
    },
    {
      "pair": "ICP-USD",
      "price": 2.802,
      "long_score": 68,
      "short_score": 20,
      "score": 68,
      "signal": "HOLD",
      "rsi14": 70.83,
      "macd_hist": 0.00317,
      "atr_pct": 1.24,
      "volume_ok": false,
      "long_reason": "price > EMA20; price > EMA50; bull EMA alignment; MACD positive; BTC bullish",
      "short_reason": "RSI fade zone; MACD weakening",
      "reason": "RSI fade zone; MACD weakening"
    },
    {
      "pair": "INJ-USD",
      "price": 5.507,
      "long_score": 68,
      "short_score": 17.0,
      "score": 68,
      "signal": "HOLD",
      "rsi14": 69.1,
      "macd_hist": 0.013751,
      "atr_pct": 1.22,
      "volume_ok": false,
      "long_reason": "price > EMA20; price > EMA50; bull EMA alignment; MACD positive; BTC bullish",
      "short_reason": "RSI fade zone; MACD weakening",
      "reason": "RSI fade zone; MACD weakening"
    },
    {
      "pair": "FET-USD",
      "price": 0.2312,
      "long_score": 68,
      "short_score": 17.0,
      "score": 68,
      "signal": "HOLD",
      "rsi14": 69.63,
      "macd_hist": 0.000304,
      "atr_pct": 1.25,
      "volume_ok": false,
      "long_reason": "price > EMA20; price > EMA50; bull EMA alignment; MACD positive; BTC bullish",
      "short_reason": "RSI fade zone; MACD weakening",
      "reason": "RSI fade zone; MACD weakening"
    },
    {
      "pair": "XRP-USD",
      "price": 1.3227,
      "long_score": 63.0,
      "short_score": 24,
      "score": 63.0,
      "signal": "HOLD",
      "rsi14": 67.6,
      "macd_hist": -6.9e-05,
      "atr_pct": 0.49,
      "volume_ok": false,
      "long_reason": "price > EMA20; price > EMA50; bull EMA alignment; RSI healthy; BTC bullish",
      "short_reason": "RSI fade zone; MACD negative; MACD weakening",
      "reason": "RSI fade zone; MACD negative; MACD weakening"
    },
    {
      "pair": "DOT-USD",
      "price": 1.218,
      "long_score": 63.0,
      "short_score": 12,
      "score": 63.0,
      "signal": "HOLD",
      "rsi14": 72.73,
      "macd_hist": 0.001192,
      "atr_pct": 0.53,
      "volume_ok": false,
      "long_reason": "price > EMA20; price > EMA50; bull EMA alignment; MACD positive; BTC bullish",
      "short_reason": "RSI fade zone; MACD weakening",
      "reason": "RSI fade zone; MACD weakening"
    },
    {
      "pair": "DOGE-USD",
      "price": 0.09976,
      "long_score": 60,
      "short_score": 9.0,
      "score": 60,
      "signal": "HOLD",
      "rsi14": 73.94,
      "macd_hist": 5.8e-05,
      "atr_pct": 0.47,
      "volume_ok": false,
      "long_reason": "price > EMA20; price > EMA50; bull EMA alignment; MACD positive; BTC bullish",
      "short_reason": "RSI fade zone; MACD weakening",
      "reason": "RSI fade zone; MACD weakening"
    },
    {
      "pair": "ADA-USD",
      "price": 0.2352,
      "long_score": 60,
      "short_score": 12,
      "score": 60,
      "signal": "HOLD",
      "rsi14": 69.23,
      "macd_hist": 7.5e-05,
      "atr_pct": 0.48,
      "volume_ok": false,
      "long_reason": "price > EMA20; price > EMA50; bull EMA alignment; MACD positive; BTC bullish",
      "short_reason": "RSI fade zone; MACD weakening",
      "reason": "RSI fade zone; MACD weakening"
    },
    {
      "pair": "UNI-USD",
      "price": 3.057,
      "long_score": 60,
      "short_score": 4,
      "score": 60,
      "signal": "HOLD",
      "rsi14": 77.08,
      "macd_hist": 0.002457,
      "atr_pct": 0.51,
      "volume_ok": false,
      "long_reason": "price > EMA20; price > EMA50; bull EMA alignment; MACD positive; BTC bullish",
      "short_reason": "MACD weakening",
      "reason": "MACD weakening"
    }
  ]
}