{
  "last_run": "2026-06-12T01:38:55.028319",
  "status": "running",
  "mode": "paper_long_short",
  "btc_trend": {
    "bullish": false,
    "bearish": false,
    "bull_score": 45,
    "bear_score": 50,
    "reason": "BTC below EMA20; BTC above EMA50; BTC EMA20 > EMA50"
  },
  "daily_realized_pnl": 0,
  "daily_trade_count": 0,
  "max_trades_per_day": 14,
  "daily_loss_limit": 3.0,
  "open_positions": 4,
  "cash": 29.616459585854756,
  "total_value": 48.37944730576133,
  "top_signals": [
    {
      "pair": "ETH-USD",
      "price": 1661.81,
      "long_score": -2.0,
      "short_score": 58.0,
      "score": 58.0,
      "signal": "HOLD",
      "rsi14": 27.61,
      "macd_hist": -2.02496,
      "atr_pct": 0.36,
      "volume_ok": false,
      "long_reason": "",
      "short_reason": "price < EMA20; price < EMA50; RSI weak; MACD negative; MACD weakening",
      "reason": "price < EMA20; price < EMA50; RSI weak; MACD negative; MACD weakening"
    },
    {
      "pair": "LTC-USD",
      "price": 42.39,
      "long_score": 7.0,
      "short_score": 57.0,
      "score": 57.0,
      "signal": "HOLD",
      "rsi14": 35.58,
      "macd_hist": -0.027079,
      "atr_pct": 0.39,
      "volume_ok": false,
      "long_reason": "RSI rebound",
      "short_reason": "price < EMA20; price < EMA50; RSI weak; MACD negative; MACD weakening",
      "reason": "price < EMA20; price < EMA50; RSI weak; MACD negative; MACD weakening"
    },
    {
      "pair": "DOT-USD",
      "price": 0.945,
      "long_score": 1.0,
      "short_score": 57.0,
      "score": 57.0,
      "signal": "HOLD",
      "rsi14": 21.43,
      "macd_hist": -0.001182,
      "atr_pct": 0.4,
      "volume_ok": false,
      "long_reason": "",
      "short_reason": "price < EMA20; price < EMA50; RSI weak; MACD negative; MACD weakening",
      "reason": "price < EMA20; price < EMA50; RSI weak; MACD negative; MACD weakening"
    },
    {
      "pair": "LINK-USD",
      "price": 7.858,
      "long_score": 6.0,
      "short_score": 56,
      "score": 56,
      "signal": "HOLD",
      "rsi14": 31.72,
      "macd_hist": -0.008884,
      "atr_pct": 0.36,
      "volume_ok": false,
      "long_reason": "RSI rebound",
      "short_reason": "price < EMA20; price < EMA50; RSI weak; MACD negative; MACD weakening",
      "reason": "price < EMA20; price < EMA50; RSI weak; MACD negative; MACD weakening"
    },
    {
      "pair": "AVAX-USD",
      "price": 6.61,
      "long_score": 9.0,
      "short_score": 56,
      "score": 56,
      "signal": "HOLD",
      "rsi14": 35.71,
      "macd_hist": -0.006128,
      "atr_pct": 0.3,
      "volume_ok": false,
      "long_reason": "RSI rebound",
      "short_reason": "price < EMA20; price < EMA50; RSI weak; MACD negative; MACD weakening",
      "reason": "price < EMA20; price < EMA50; RSI weak; MACD negative; MACD weakening"
    },
    {
      "pair": "NEAR-USD",
      "price": 2.033,
      "long_score": -2.0,
      "short_score": 56.0,
      "score": 56.0,
      "signal": "HOLD",
      "rsi14": 28.26,
      "macd_hist": -0.005078,
      "atr_pct": 0.83,
      "volume_ok": false,
      "long_reason": "",
      "short_reason": "price < EMA20; price < EMA50; RSI weak; MACD negative; MACD weakening",
      "reason": "price < EMA20; price < EMA50; RSI weak; MACD negative; MACD weakening"
    },
    {
      "pair": "DOGE-USD",
      "price": 0.08556,
      "long_score": 0,
      "short_score": 55.0,
      "score": 55.0,
      "signal": "HOLD",
      "rsi14": 25.97,
      "macd_hist": -0.000103,
      "atr_pct": 0.33,
      "volume_ok": false,
      "long_reason": "",
      "short_reason": "price < EMA20; price < EMA50; RSI weak; MACD negative; MACD weakening",
      "reason": "price < EMA20; price < EMA50; RSI weak; MACD negative; MACD weakening"
    },
    {
      "pair": "BTC-USD",
      "price": 63279.2,
      "long_score": 33.0,
      "short_score": 47.0,
      "score": 47.0,
      "signal": "HOLD",
      "rsi14": 36.83,
      "macd_hist": -43.370656,
      "atr_pct": 0.27,
      "volume_ok": false,
      "long_reason": "price > EMA50; bull EMA alignment; RSI rebound",
      "short_reason": "price < EMA20; RSI weak; MACD negative; MACD weakening",
      "reason": "price < EMA20; RSI weak; MACD negative; MACD weakening"
    },
    {
      "pair": "SOL-USD",
      "price": 66.42,
      "long_score": 17.0,
      "short_score": 46,
      "score": 46,
      "signal": "HOLD",
      "rsi14": 30.34,
      "macd_hist": -0.086075,
      "atr_pct": 0.39,
      "volume_ok": false,
      "long_reason": "price > EMA50; RSI rebound",
      "short_reason": "price < EMA20; RSI weak; MACD negative; MACD weakening",
      "reason": "price < EMA20; RSI weak; MACD negative; MACD weakening"
    },
    {
      "pair": "XRP-USD",
      "price": 1.1363,
      "long_score": 37.0,
      "short_score": 45.0,
      "score": 45.0,
      "signal": "HOLD",
      "rsi14": 33.66,
      "macd_hist": -0.001273,
      "atr_pct": 0.33,
      "volume_ok": false,
      "long_reason": "price > EMA50; bull EMA alignment; RSI rebound",
      "short_reason": "price < EMA20; RSI weak; MACD negative; MACD weakening",
      "reason": "price < EMA20; RSI weak; MACD negative; MACD weakening"
    },
    {
      "pair": "INJ-USD",
      "price": 5.379,
      "long_score": 37.0,
      "short_score": 44.0,
      "score": 44.0,
      "signal": "HOLD",
      "rsi14": 37.36,
      "macd_hist": -0.009894,
      "atr_pct": 0.87,
      "volume_ok": false,
      "long_reason": "price > EMA50; bull EMA alignment; RSI rebound",
      "short_reason": "price < EMA20; RSI weak; MACD negative; MACD weakening",
      "reason": "price < EMA20; RSI weak; MACD negative; MACD weakening"
    },
    {
      "pair": "AAVE-USD",
      "price": 64.02,
      "long_score": 27.0,
      "short_score": 37.0,
      "score": 37.0,
      "signal": "HOLD",
      "rsi14": 32.33,
      "macd_hist": -0.064871,
      "atr_pct": 0.38,
      "volume_ok": false,
      "long_reason": "price > EMA50; RSI rebound; MACD improving",
      "short_reason": "price < EMA20; RSI weak; MACD negative",
      "reason": "price < EMA20; RSI weak; MACD negative"
    }
  ],
  "expectancy": -0.020649856927541087,
  "profit_factor": 0.7155989785891126,
  "win_rate": 35.82089552238806,
  "auto_pause_active": false,
  "auto_pause_reason": ""
}