{
  "last_run": "2026-05-29T15:03:20.730089",
  "status": "running",
  "mode": "paper_long_short",
  "btc_trend": {
    "bullish": false,
    "bearish": true,
    "bull_score": 0,
    "bear_score": 95,
    "reason": "BTC below EMA20; BTC below EMA50; BTC EMA20 < EMA50"
  },
  "daily_realized_pnl": -0.2073053130844748,
  "daily_trade_count": 14,
  "max_trades_per_day": 14,
  "daily_loss_limit": 3.0,
  "open_positions": 4,
  "cash": 31.468765017545458,
  "total_value": 49.383203585987225,
  "top_signals": [
    {
      "pair": "NEAR-USD",
      "price": 2.446,
      "long_score": 20,
      "short_score": 83.0,
      "score": 83.0,
      "signal": "STRONG_SHORT",
      "rsi14": 41.51,
      "macd_hist": -0.000238,
      "atr_pct": 1.34,
      "volume_ok": false,
      "long_reason": "RSI rebound; MACD improving",
      "short_reason": "price < EMA20; price < EMA50; bear EMA alignment; RSI weak; MACD negative; BTC bearish",
      "reason": "price < EMA20; price < EMA50; bear EMA alignment; RSI weak; MACD negative; BTC bearish"
    },
    {
      "pair": "ATOM-USD",
      "price": 1.993,
      "long_score": 20,
      "short_score": 80,
      "score": 80,
      "signal": "SHORT",
      "rsi14": 32.22,
      "macd_hist": -0.000997,
      "atr_pct": 0.67,
      "volume_ok": true,
      "long_reason": "RSI rebound; MACD improving; volume active",
      "short_reason": "price < EMA20; price < EMA50; bear EMA alignment; RSI weak; MACD negative; volume active; BTC bearish",
      "reason": "price < EMA20; price < EMA50; bear EMA alignment; RSI weak; MACD negative; volume active; BTC bearish"
    },
    {
      "pair": "HBAR-USD",
      "price": 0.08936,
      "long_score": 17.0,
      "short_score": 80,
      "score": 80,
      "signal": "SHORT",
      "rsi14": 36.55,
      "macd_hist": -7.6e-05,
      "atr_pct": 0.89,
      "volume_ok": true,
      "long_reason": "RSI rebound; MACD improving; volume active",
      "short_reason": "price < EMA20; price < EMA50; bear EMA alignment; RSI weak; MACD negative; volume active; BTC bearish",
      "reason": "price < EMA20; price < EMA50; bear EMA alignment; RSI weak; MACD negative; volume active; BTC bearish"
    },
    {
      "pair": "APT-USD",
      "price": 0.9072,
      "long_score": 20,
      "short_score": 80,
      "score": 80,
      "signal": "SHORT",
      "rsi14": 40.82,
      "macd_hist": -0.000442,
      "atr_pct": 0.89,
      "volume_ok": true,
      "long_reason": "RSI rebound; MACD improving; volume active",
      "short_reason": "price < EMA20; price < EMA50; bear EMA alignment; RSI weak; MACD negative; volume active; BTC bearish",
      "reason": "price < EMA20; price < EMA50; bear EMA alignment; RSI weak; MACD negative; volume active; BTC bearish"
    },
    {
      "pair": "ARB-USD",
      "price": 0.1023,
      "long_score": 20,
      "short_score": 80,
      "score": 80,
      "signal": "SHORT",
      "rsi14": 35.0,
      "macd_hist": -0.000133,
      "atr_pct": 0.73,
      "volume_ok": true,
      "long_reason": "RSI rebound; MACD improving; volume active",
      "short_reason": "price < EMA20; price < EMA50; bear EMA alignment; RSI weak; MACD negative; volume active; BTC bearish",
      "reason": "price < EMA20; price < EMA50; bear EMA alignment; RSI weak; MACD negative; volume active; BTC bearish"
    },
    {
      "pair": "SEI-USD",
      "price": 0.06352,
      "long_score": 12,
      "short_score": 77.0,
      "score": 77.0,
      "signal": "SHORT",
      "rsi14": 16.21,
      "macd_hist": -0.000216,
      "atr_pct": 1.04,
      "volume_ok": false,
      "long_reason": "MACD improving",
      "short_reason": "price < EMA20; price < EMA50; bear EMA alignment; RSI weak; MACD negative; BTC bearish",
      "reason": "price < EMA20; price < EMA50; bear EMA alignment; RSI weak; MACD negative; BTC bearish"
    },
    {
      "pair": "BTC-USD",
      "price": 73002.35,
      "long_score": 9.0,
      "short_score": 75.0,
      "score": 75.0,
      "signal": "SHORT",
      "rsi14": 39.49,
      "macd_hist": -27.152983,
      "atr_pct": 0.38,
      "volume_ok": false,
      "long_reason": "RSI rebound; MACD improving",
      "short_reason": "price < EMA20; price < EMA50; bear EMA alignment; RSI weak; MACD negative; BTC bearish",
      "reason": "price < EMA20; price < EMA50; bear EMA alignment; RSI weak; MACD negative; BTC bearish"
    },
    {
      "pair": "SHIB-USD",
      "price": 5.32e-06,
      "long_score": 15.0,
      "short_score": 75.0,
      "score": 75.0,
      "signal": "SHORT",
      "rsi14": 33.33,
      "macd_hist": -0.0,
      "atr_pct": 0.77,
      "volume_ok": false,
      "long_reason": "RSI rebound; MACD improving",
      "short_reason": "price < EMA20; price < EMA50; bear EMA alignment; RSI weak; MACD negative; BTC bearish",
      "reason": "price < EMA20; price < EMA50; bear EMA alignment; RSI weak; MACD negative; BTC bearish"
    },
    {
      "pair": "FET-USD",
      "price": 0.2352,
      "long_score": 44,
      "short_score": 73.0,
      "score": 73.0,
      "signal": "SHORT",
      "rsi14": 44.71,
      "macd_hist": -6.6e-05,
      "atr_pct": 1.26,
      "volume_ok": true,
      "long_reason": "price > EMA20; RSI healthy; MACD improving; volume active",
      "short_reason": "price < EMA50; bear EMA alignment; RSI weak; MACD negative; volume active; BTC bearish",
      "reason": "price < EMA50; bear EMA alignment; RSI weak; MACD negative; volume active; BTC bearish"
    },
    {
      "pair": "SOL-USD",
      "price": 81.22,
      "long_score": 9.0,
      "short_score": 72,
      "score": 72,
      "signal": "SHORT",
      "rsi14": 40.0,
      "macd_hist": -0.037498,
      "atr_pct": 0.54,
      "volume_ok": false,
      "long_reason": "RSI rebound; MACD improving",
      "short_reason": "price < EMA20; price < EMA50; bear EMA alignment; RSI weak; MACD negative; BTC bearish",
      "reason": "price < EMA20; price < EMA50; bear EMA alignment; RSI weak; MACD negative; BTC bearish"
    },
    {
      "pair": "XRP-USD",
      "price": 1.3059,
      "long_score": 19.0,
      "short_score": 72,
      "score": 72,
      "signal": "SHORT",
      "rsi14": 44.8,
      "macd_hist": -2.7e-05,
      "atr_pct": 0.48,
      "volume_ok": false,
      "long_reason": "RSI healthy; MACD improving",
      "short_reason": "price < EMA20; price < EMA50; bear EMA alignment; RSI weak; MACD negative; BTC bearish",
      "reason": "price < EMA20; price < EMA50; bear EMA alignment; RSI weak; MACD negative; BTC bearish"
    },
    {
      "pair": "ADA-USD",
      "price": 0.2322,
      "long_score": 16,
      "short_score": 72,
      "score": 72,
      "signal": "SHORT",
      "rsi14": 43.53,
      "macd_hist": -2.6e-05,
      "atr_pct": 0.55,
      "volume_ok": false,
      "long_reason": "RSI healthy; MACD improving",
      "short_reason": "price < EMA20; price < EMA50; bear EMA alignment; RSI weak; MACD negative; BTC bearish",
      "reason": "price < EMA20; price < EMA50; bear EMA alignment; RSI weak; MACD negative; BTC bearish"
    }
  ]
}