{
  "last_run": "2026-05-31T18:02:03.141207",
  "status": "running",
  "mode": "paper_long_short",
  "btc_trend": {
    "bullish": false,
    "bearish": false,
    "bull_score": 55,
    "bear_score": 45,
    "reason": "BTC above EMA20; BTC below EMA50; BTC EMA20 < EMA50"
  },
  "daily_realized_pnl": 0,
  "daily_trade_count": 0,
  "max_trades_per_day": 14,
  "daily_loss_limit": 3.0,
  "open_positions": 4,
  "cash": 32.70380081670621,
  "total_value": 48.744871869453924,
  "top_signals": [
    {
      "pair": "ATOM-USD",
      "price": 1.929,
      "long_score": 18,
      "short_score": 72,
      "score": 72,
      "signal": "SHORT",
      "rsi14": 9.3,
      "macd_hist": -0.001378,
      "atr_pct": 0.4,
      "volume_ok": true,
      "long_reason": "MACD improving; volume active",
      "short_reason": "price < EMA20; price < EMA50; bear EMA alignment; RSI weak; MACD negative; volume active",
      "reason": "price < EMA20; price < EMA50; bear EMA alignment; RSI weak; MACD negative; volume active"
    },
    {
      "pair": "MATIC-USD",
      "price": 0.1995,
      "long_score": 72,
      "short_score": 24,
      "score": 72,
      "signal": "BUY",
      "rsi14": 65.19,
      "macd_hist": 0.000748,
      "atr_pct": 1.17,
      "volume_ok": true,
      "long_reason": "price > EMA20; price > EMA50; RSI healthy; MACD positive; MACD improving; volume active",
      "short_reason": "RSI fade zone; volume active",
      "reason": "price > EMA20; price > EMA50; RSI healthy; MACD positive; MACD improving; volume active"
    },
    {
      "pair": "FET-USD",
      "price": 0.2626,
      "long_score": 26,
      "short_score": 69.0,
      "score": 69.0,
      "signal": "HOLD",
      "rsi14": 38.82,
      "macd_hist": -0.000349,
      "atr_pct": 1.05,
      "volume_ok": false,
      "long_reason": "RSI rebound; MACD improving",
      "short_reason": "price < EMA20; price < EMA50; bear EMA alignment; RSI weak; MACD negative",
      "reason": "price < EMA20; price < EMA50; bear EMA alignment; RSI weak; MACD negative"
    },
    {
      "pair": "ETH-USD",
      "price": 2002.56,
      "long_score": 15.0,
      "short_score": 67.0,
      "score": 67.0,
      "signal": "HOLD",
      "rsi14": 41.08,
      "macd_hist": -0.168722,
      "atr_pct": 0.27,
      "volume_ok": false,
      "long_reason": "RSI rebound; MACD improving",
      "short_reason": "price < EMA20; price < EMA50; bear EMA alignment; RSI weak; MACD negative",
      "reason": "price < EMA20; price < EMA50; bear EMA alignment; RSI weak; MACD negative"
    },
    {
      "pair": "FIL-USD",
      "price": 0.929,
      "long_score": 15.0,
      "short_score": 66.0,
      "score": 66.0,
      "signal": "HOLD",
      "rsi14": 31.25,
      "macd_hist": -0.000436,
      "atr_pct": 0.58,
      "volume_ok": false,
      "long_reason": "RSI rebound; MACD improving",
      "short_reason": "price < EMA20; price < EMA50; bear EMA alignment; RSI weak; MACD negative",
      "reason": "price < EMA20; price < EMA50; bear EMA alignment; RSI weak; MACD negative"
    },
    {
      "pair": "ADA-USD",
      "price": 0.233,
      "long_score": 18,
      "short_score": 64,
      "score": 64,
      "signal": "HOLD",
      "rsi14": 38.64,
      "macd_hist": -4.5e-05,
      "atr_pct": 0.36,
      "volume_ok": false,
      "long_reason": "RSI rebound; MACD improving",
      "short_reason": "price < EMA20; price < EMA50; bear EMA alignment; RSI weak; MACD negative",
      "reason": "price < EMA20; price < EMA50; bear EMA alignment; RSI weak; MACD negative"
    },
    {
      "pair": "AVAX-USD",
      "price": 8.85,
      "long_score": 21.0,
      "short_score": 64,
      "score": 64,
      "signal": "HOLD",
      "rsi14": 40.0,
      "macd_hist": -0.001798,
      "atr_pct": 0.3,
      "volume_ok": false,
      "long_reason": "RSI rebound; MACD improving",
      "short_reason": "price < EMA20; price < EMA50; bear EMA alignment; RSI weak; MACD negative",
      "reason": "price < EMA20; price < EMA50; bear EMA alignment; RSI weak; MACD negative"
    },
    {
      "pair": "LINK-USD",
      "price": 9.048,
      "long_score": 15.0,
      "short_score": 64,
      "score": 64,
      "signal": "HOLD",
      "rsi14": 38.5,
      "macd_hist": -0.002525,
      "atr_pct": 0.34,
      "volume_ok": false,
      "long_reason": "RSI rebound; MACD improving",
      "short_reason": "price < EMA20; price < EMA50; bear EMA alignment; RSI weak; MACD negative",
      "reason": "price < EMA20; price < EMA50; bear EMA alignment; RSI weak; MACD negative"
    },
    {
      "pair": "DOT-USD",
      "price": 1.165,
      "long_score": 25.0,
      "short_score": 64,
      "score": 64,
      "signal": "HOLD",
      "rsi14": 44.83,
      "macd_hist": -0.000359,
      "atr_pct": 0.45,
      "volume_ok": false,
      "long_reason": "RSI healthy; MACD improving",
      "short_reason": "price < EMA20; price < EMA50; bear EMA alignment; RSI weak; MACD negative",
      "reason": "price < EMA20; price < EMA50; bear EMA alignment; RSI weak; MACD negative"
    },
    {
      "pair": "LTC-USD",
      "price": 51.63,
      "long_score": 15.0,
      "short_score": 64,
      "score": 64,
      "signal": "HOLD",
      "rsi14": 36.61,
      "macd_hist": -0.023345,
      "atr_pct": 0.3,
      "volume_ok": false,
      "long_reason": "RSI rebound; MACD improving",
      "short_reason": "price < EMA20; price < EMA50; bear EMA alignment; RSI weak; MACD negative",
      "reason": "price < EMA20; price < EMA50; bear EMA alignment; RSI weak; MACD negative"
    },
    {
      "pair": "HBAR-USD",
      "price": 0.09506,
      "long_score": 15.0,
      "short_score": 64,
      "score": 64,
      "signal": "HOLD",
      "rsi14": 37.41,
      "macd_hist": -3.1e-05,
      "atr_pct": 0.57,
      "volume_ok": false,
      "long_reason": "RSI rebound; MACD improving",
      "short_reason": "price < EMA20; price < EMA50; bear EMA alignment; RSI weak; MACD negative",
      "reason": "price < EMA20; price < EMA50; bear EMA alignment; RSI weak; MACD negative"
    },
    {
      "pair": "OP-USD",
      "price": 0.116,
      "long_score": 15.0,
      "short_score": 64.0,
      "score": 64.0,
      "signal": "HOLD",
      "rsi14": 37.5,
      "macd_hist": -0.000124,
      "atr_pct": 0.8,
      "volume_ok": false,
      "long_reason": "RSI rebound; MACD improving",
      "short_reason": "price < EMA20; price < EMA50; bear EMA alignment; RSI weak; MACD negative",
      "reason": "price < EMA20; price < EMA50; bear EMA alignment; RSI weak; MACD negative"
    }
  ]
}