{
  "last_run": "2026-06-09T03:23:47.321721",
  "status": "running",
  "mode": "paper_long_short",
  "btc_trend": {
    "bullish": false,
    "bearish": true,
    "bull_score": 15,
    "bear_score": 80,
    "reason": "BTC below EMA20; BTC below EMA50; BTC EMA20 < EMA50"
  },
  "daily_realized_pnl": 0,
  "daily_trade_count": 0,
  "max_trades_per_day": 14,
  "daily_loss_limit": 3.0,
  "open_positions": 3,
  "cash": 34.62409074642709,
  "total_value": 48.394631336424304,
  "top_signals": [
    {
      "pair": "ETH-USD",
      "price": 1667.87,
      "long_score": 2.0,
      "short_score": 74.0,
      "score": 74.0,
      "signal": "SHORT",
      "rsi14": 28.25,
      "macd_hist": -0.677588,
      "atr_pct": 0.56,
      "volume_ok": false,
      "long_reason": "MACD improving",
      "short_reason": "price < EMA20; price < EMA50; bear EMA alignment; RSI weak; MACD negative; BTC bearish",
      "reason": "price < EMA20; price < EMA50; bear EMA alignment; RSI weak; MACD negative; BTC bearish"
    },
    {
      "pair": "AAVE-USD",
      "price": 61.98,
      "long_score": 4,
      "short_score": 73.0,
      "score": 73.0,
      "signal": "SHORT",
      "rsi14": 20.24,
      "macd_hist": -0.026053,
      "atr_pct": 0.6,
      "volume_ok": false,
      "long_reason": "MACD improving",
      "short_reason": "price < EMA20; price < EMA50; bear EMA alignment; RSI weak; MACD negative; BTC bearish",
      "reason": "price < EMA20; price < EMA50; bear EMA alignment; RSI weak; MACD negative; BTC bearish"
    },
    {
      "pair": "XRP-USD",
      "price": 1.155,
      "long_score": 13.0,
      "short_score": 71.0,
      "score": 71.0,
      "signal": "HOLD",
      "rsi14": 32.7,
      "macd_hist": -0.000199,
      "atr_pct": 0.52,
      "volume_ok": false,
      "long_reason": "RSI rebound; MACD improving",
      "short_reason": "price < EMA20; price < EMA50; bear EMA alignment; RSI weak; MACD negative; BTC bearish",
      "reason": "price < EMA20; price < EMA50; bear EMA alignment; RSI weak; MACD negative; BTC bearish"
    },
    {
      "pair": "NEAR-USD",
      "price": 2.075,
      "long_score": 22.0,
      "short_score": 68.0,
      "score": 68.0,
      "signal": "HOLD",
      "rsi14": 27.87,
      "macd_hist": 0.000151,
      "atr_pct": 1.07,
      "volume_ok": false,
      "long_reason": "MACD positive; MACD improving",
      "short_reason": "price < EMA20; price < EMA50; bear EMA alignment; RSI weak; BTC bearish",
      "reason": "price < EMA20; price < EMA50; bear EMA alignment; RSI weak; BTC bearish"
    },
    {
      "pair": "BTC-USD",
      "price": 62855.88,
      "long_score": 25.0,
      "short_score": 61.0,
      "score": 61.0,
      "signal": "HOLD",
      "rsi14": 42.47,
      "macd_hist": 27.736008,
      "atr_pct": 0.35,
      "volume_ok": false,
      "long_reason": "RSI healthy; MACD positive; MACD improving",
      "short_reason": "price < EMA20; price < EMA50; bear EMA alignment; RSI weak; BTC bearish",
      "reason": "price < EMA20; price < EMA50; bear EMA alignment; RSI weak; BTC bearish"
    },
    {
      "pair": "LTC-USD",
      "price": 42.62,
      "long_score": 23.0,
      "short_score": 61.0,
      "score": 61.0,
      "signal": "HOLD",
      "rsi14": 34.68,
      "macd_hist": 0.014813,
      "atr_pct": 0.53,
      "volume_ok": false,
      "long_reason": "RSI rebound; MACD positive; MACD improving",
      "short_reason": "price < EMA20; price < EMA50; bear EMA alignment; RSI weak; BTC bearish",
      "reason": "price < EMA20; price < EMA50; bear EMA alignment; RSI weak; BTC bearish"
    },
    {
      "pair": "DOT-USD",
      "price": 0.959,
      "long_score": 25.0,
      "short_score": 61.0,
      "score": 61.0,
      "signal": "HOLD",
      "rsi14": 30.95,
      "macd_hist": 0.000243,
      "atr_pct": 0.56,
      "volume_ok": false,
      "long_reason": "RSI rebound; MACD positive; MACD improving",
      "short_reason": "price < EMA20; price < EMA50; bear EMA alignment; RSI weak; BTC bearish",
      "reason": "price < EMA20; price < EMA50; bear EMA alignment; RSI weak; BTC bearish"
    },
    {
      "pair": "SOL-USD",
      "price": 66.02,
      "long_score": 23.0,
      "short_score": 60,
      "score": 60,
      "signal": "HOLD",
      "rsi14": 34.98,
      "macd_hist": 0.022147,
      "atr_pct": 0.59,
      "volume_ok": false,
      "long_reason": "RSI rebound; MACD positive; MACD improving",
      "short_reason": "price < EMA20; price < EMA50; bear EMA alignment; RSI weak; BTC bearish",
      "reason": "price < EMA20; price < EMA50; bear EMA alignment; RSI weak; BTC bearish"
    },
    {
      "pair": "LINK-USD",
      "price": 7.878,
      "long_score": 14.0,
      "short_score": 60,
      "score": 60,
      "signal": "HOLD",
      "rsi14": 28.68,
      "macd_hist": 0.001696,
      "atr_pct": 0.55,
      "volume_ok": false,
      "long_reason": "MACD positive; MACD improving",
      "short_reason": "price < EMA20; price < EMA50; bear EMA alignment; RSI weak; BTC bearish",
      "reason": "price < EMA20; price < EMA50; bear EMA alignment; RSI weak; BTC bearish"
    },
    {
      "pair": "AVAX-USD",
      "price": 6.66,
      "long_score": 17.0,
      "short_score": 60,
      "score": 60,
      "signal": "HOLD",
      "rsi14": 29.63,
      "macd_hist": 0.00199,
      "atr_pct": 0.58,
      "volume_ok": false,
      "long_reason": "MACD positive; MACD improving",
      "short_reason": "price < EMA20; price < EMA50; bear EMA alignment; RSI weak; BTC bearish",
      "reason": "price < EMA20; price < EMA50; bear EMA alignment; RSI weak; BTC bearish"
    },
    {
      "pair": "DOGE-USD",
      "price": 0.08524,
      "long_score": 24,
      "short_score": 59.0,
      "score": 59.0,
      "signal": "HOLD",
      "rsi14": 31.1,
      "macd_hist": 1.2e-05,
      "atr_pct": 0.53,
      "volume_ok": false,
      "long_reason": "RSI rebound; MACD positive; MACD improving",
      "short_reason": "price < EMA20; price < EMA50; bear EMA alignment; RSI weak; BTC bearish",
      "reason": "price < EMA20; price < EMA50; bear EMA alignment; RSI weak; BTC bearish"
    },
    {
      "pair": "INJ-USD",
      "price": 5.544,
      "long_score": 25.0,
      "short_score": 58.0,
      "score": 58.0,
      "signal": "HOLD",
      "rsi14": 35.57,
      "macd_hist": 0.003481,
      "atr_pct": 0.99,
      "volume_ok": false,
      "long_reason": "RSI rebound; MACD positive; MACD improving",
      "short_reason": "price < EMA20; price < EMA50; bear EMA alignment; RSI weak; BTC bearish",
      "reason": "price < EMA20; price < EMA50; bear EMA alignment; RSI weak; BTC bearish"
    }
  ],
  "expectancy": -0.02084710990261994,
  "profit_factor": 0.7167232764982451,
  "win_rate": 36.36363636363637,
  "auto_pause_active": false,
  "auto_pause_reason": ""
}