[
  {
    "time": "2026-06-05T20:05:08.936748",
    "pair": "INJ-USD",
    "old_signal": "HOLD",
    "new_signal": "SHORT"
  },
  {
    "time": "2026-06-05T20:05:08.936752",
    "pair": "BTC-USD",
    "old_signal": "SHORT",
    "new_signal": "HOLD"
  },
  {
    "time": "2026-06-05T20:05:08.936756",
    "pair": "ETH-USD",
    "old_signal": "STRONG_SHORT",
    "new_signal": "HOLD"
  },
  {
    "time": "2026-06-05T20:05:08.936761",
    "pair": "XRP-USD",
    "old_signal": "SHORT",
    "new_signal": "HOLD"
  },
  {
    "time": "2026-06-05T20:20:13.457617",
    "pair": "AAVE-USD",
    "old_signal": "SHORT",
    "new_signal": "HOLD"
  },
  {
    "time": "2026-06-05T20:20:13.457626",
    "pair": "LTC-USD",
    "old_signal": "SHORT",
    "new_signal": "HOLD"
  },
  {
    "time": "2026-06-05T20:20:13.457630",
    "pair": "DOT-USD",
    "old_signal": "SHORT",
    "new_signal": "HOLD"
  },
  {
    "time": "2026-06-05T20:20:13.457633",
    "pair": "AVAX-USD",
    "old_signal": "SHORT",
    "new_signal": "HOLD"
  },
  {
    "time": "2026-06-05T20:20:13.457637",
    "pair": "INJ-USD",
    "old_signal": "SHORT",
    "new_signal": "HOLD"
  },
  {
    "time": "2026-06-05T20:20:13.457641",
    "pair": "SOL-USD",
    "old_signal": "SHORT",
    "new_signal": "HOLD"
  },
  {
    "time": "2026-06-05T20:20:13.457644",
    "pair": "LINK-USD",
    "old_signal": "SHORT",
    "new_signal": "HOLD"
  },
  {
    "time": "2026-06-05T20:20:13.457648",
    "pair": "DOGE-USD",
    "old_signal": "SHORT",
    "new_signal": "HOLD"
  },
  {
    "time": "2026-06-05T22:05:37.333630",
    "pair": "INJ-USD",
    "old_signal": "HOLD",
    "new_signal": "BUY"
  },
  {
    "time": "2026-06-05T22:20:41.506337",
    "pair": "INJ-USD",
    "old_signal": "BUY",
    "new_signal": "HOLD"
  },
  {
    "time": "2026-06-05T23:20:58.604688",
    "pair": "AVAX-USD",
    "old_signal": "HOLD",
    "new_signal": "SHORT"
  },
  {
    "time": "2026-06-05T23:20:58.604698",
    "pair": "SOL-USD",
    "old_signal": "HOLD",
    "new_signal": "SHORT"
  },
  {
    "time": "2026-06-05T23:36:02.701547",
    "pair": "AVAX-USD",
    "old_signal": "SHORT",
    "new_signal": "STRONG_SHORT"
  },
  {
    "time": "2026-06-05T23:36:02.701556",
    "pair": "NEAR-USD",
    "old_signal": "HOLD",
    "new_signal": "STRONG_SHORT"
  },
  {
    "time": "2026-06-05T23:36:02.701560",
    "pair": "ETH-USD",
    "old_signal": "HOLD",
    "new_signal": "STRONG_SHORT"
  },
  {
    "time": "2026-06-05T23:36:02.701564",
    "pair": "LTC-USD",
    "old_signal": "HOLD",
    "new_signal": "STRONG_SHORT"
  },
  {
    "time": "2026-06-05T23:36:02.701567",
    "pair": "SOL-USD",
    "old_signal": "SHORT",
    "new_signal": "STRONG_SHORT"
  },
  {
    "time": "2026-06-05T23:36:02.701571",
    "pair": "LINK-USD",
    "old_signal": "HOLD",
    "new_signal": "STRONG_SHORT"
  },
  {
    "time": "2026-06-05T23:36:02.701574",
    "pair": "XRP-USD",
    "old_signal": "HOLD",
    "new_signal": "SHORT"
  },
  {
    "time": "2026-06-05T23:51:06.904771",
    "pair": "DOGE-USD",
    "old_signal": "HOLD",
    "new_signal": "SHORT"
  },
  {
    "time": "2026-06-05T23:51:06.904779",
    "pair": "LTC-USD",
    "old_signal": "STRONG_SHORT",
    "new_signal": "HOLD"
  },
  {
    "time": "2026-06-06T00:06:11.106870",
    "pair": "AVAX-USD",
    "old_signal": "STRONG_SHORT",
    "new_signal": "SHORT"
  },
  {
    "time": "2026-06-06T00:06:11.106880",
    "pair": "NEAR-USD",
    "old_signal": "STRONG_SHORT",
    "new_signal": "SHORT"
  },
  {
    "time": "2026-06-06T00:06:11.106884",
    "pair": "ETH-USD",
    "old_signal": "STRONG_SHORT",
    "new_signal": "SHORT"
  },
  {
    "time": "2026-06-06T00:06:11.106889",
    "pair": "XRP-USD",
    "old_signal": "SHORT",
    "new_signal": "HOLD"
  },
  {
    "time": "2026-06-06T00:06:11.106892",
    "pair": "DOGE-USD",
    "old_signal": "SHORT",
    "new_signal": "HOLD"
  },
  {
    "time": "2026-06-06T00:06:11.106897",
    "pair": "SOL-USD",
    "old_signal": "STRONG_SHORT",
    "new_signal": "HOLD"
  },
  {
    "time": "2026-06-06T00:06:11.106901",
    "pair": "LINK-USD",
    "old_signal": "STRONG_SHORT",
    "new_signal": "HOLD"
  },
  {
    "time": "2026-06-06T00:21:15.361051",
    "pair": "AVAX-USD",
    "old_signal": "SHORT",
    "new_signal": "HOLD"
  },
  {
    "time": "2026-06-06T00:21:15.361061",
    "pair": "ETH-USD",
    "old_signal": "SHORT",
    "new_signal": "HOLD"
  },
  {
    "time": "2026-06-06T00:51:24.489539",
    "pair": "NEAR-USD",
    "old_signal": "SHORT",
    "new_signal": "HOLD"
  },
  {
    "time": "2026-06-06T01:21:33.222037",
    "pair": "AAVE-USD",
    "old_signal": "HOLD",
    "new_signal": "SHORT"
  },
  {
    "time": "2026-06-06T01:21:33.222054",
    "pair": "ETH-USD",
    "old_signal": "HOLD",
    "new_signal": "SHORT"
  },
  {
    "time": "2026-06-06T01:36:37.312379",
    "pair": "AAVE-USD",
    "old_signal": "SHORT",
    "new_signal": "HOLD"
  },
  {
    "time": "2026-06-06T01:36:37.312391",
    "pair": "ETH-USD",
    "old_signal": "SHORT",
    "new_signal": "HOLD"
  },
  {
    "time": "2026-06-06T01:51:41.437277",
    "pair": "AAVE-USD",
    "old_signal": "HOLD",
    "new_signal": "STRONG_SHORT"
  },
  {
    "time": "2026-06-06T01:51:41.437288",
    "pair": "BTC-USD",
    "old_signal": "HOLD",
    "new_signal": "STRONG_SHORT"
  },
  {
    "time": "2026-06-06T02:06:45.502346",
    "pair": "ETH-USD",
    "old_signal": "HOLD",
    "new_signal": "STRONG_SHORT"
  },
  {
    "time": "2026-06-06T02:06:45.502357",
    "pair": "DOT-USD",
    "old_signal": "HOLD",
    "new_signal": "STRONG_SHORT"
  },
  {
    "time": "2026-06-06T02:06:45.502361",
    "pair": "SOL-USD",
    "old_signal": "HOLD",
    "new_signal": "STRONG_SHORT"
  },
  {
    "time": "2026-06-06T02:06:45.502365",
    "pair": "LINK-USD",
    "old_signal": "HOLD",
    "new_signal": "STRONG_SHORT"
  },
  {
    "time": "2026-06-06T02:06:45.502368",
    "pair": "AVAX-USD",
    "old_signal": "HOLD",
    "new_signal": "STRONG_SHORT"
  },
  {
    "time": "2026-06-06T02:06:45.502372",
    "pair": "XRP-USD",
    "old_signal": "HOLD",
    "new_signal": "SHORT"
  },
  {
    "time": "2026-06-06T02:06:45.502375",
    "pair": "DOGE-USD",
    "old_signal": "HOLD",
    "new_signal": "SHORT"
  },
  {
    "time": "2026-06-06T02:21:49.998157",
    "pair": "NEAR-USD",
    "old_signal": "HOLD",
    "new_signal": "STRONG_SHORT"
  },
  {
    "time": "2026-06-06T02:21:49.998167",
    "pair": "LTC-USD",
    "old_signal": "HOLD",
    "new_signal": "STRONG_SHORT"
  },
  {
    "time": "2026-06-06T02:36:54.143998",
    "pair": "BTC-USD",
    "old_signal": "STRONG_SHORT",
    "new_signal": "SHORT"
  },
  {
    "time": "2026-06-06T02:36:54.144012",
    "pair": "AAVE-USD",
    "old_signal": "STRONG_SHORT",
    "new_signal": "SHORT"
  },
  {
    "time": "2026-06-06T02:36:54.144016",
    "pair": "LTC-USD",
    "old_signal": "STRONG_SHORT",
    "new_signal": "HOLD"
  },
  {
    "time": "2026-06-06T02:36:54.144019",
    "pair": "AVAX-USD",
    "old_signal": "STRONG_SHORT",
    "new_signal": "HOLD"
  },
  {
    "time": "2026-06-06T02:36:54.144022",
    "pair": "DOT-USD",
    "old_signal": "STRONG_SHORT",
    "new_signal": "HOLD"
  },
  {
    "time": "2026-06-06T02:36:54.144026",
    "pair": "SOL-USD",
    "old_signal": "STRONG_SHORT",
    "new_signal": "HOLD"
  },
  {
    "time": "2026-06-06T02:36:54.144030",
    "pair": "NEAR-USD",
    "old_signal": "STRONG_SHORT",
    "new_signal": "HOLD"
  },
  {
    "time": "2026-06-06T02:51:58.288485",
    "pair": "DOGE-USD",
    "old_signal": "SHORT",
    "new_signal": "HOLD"
  },
  {
    "time": "2026-06-06T02:51:58.288493",
    "pair": "ETH-USD",
    "old_signal": "STRONG_SHORT",
    "new_signal": "HOLD"
  },
  {
    "time": "2026-06-06T02:51:58.288497",
    "pair": "LINK-USD",
    "old_signal": "STRONG_SHORT",
    "new_signal": "HOLD"
  },
  {
    "time": "2026-06-06T02:51:58.288501",
    "pair": "XRP-USD",
    "old_signal": "SHORT",
    "new_signal": "HOLD"
  },
  {
    "time": "2026-06-06T02:51:58.288505",
    "pair": "BTC-USD",
    "old_signal": "SHORT",
    "new_signal": "HOLD"
  },
  {
    "time": "2026-06-06T03:07:02.402823",
    "pair": "AAVE-USD",
    "old_signal": "SHORT",
    "new_signal": "STRONG_SHORT"
  },
  {
    "time": "2026-06-06T03:07:02.402831",
    "pair": "AVAX-USD",
    "old_signal": "HOLD",
    "new_signal": "STRONG_SHORT"
  },
  {
    "time": "2026-06-06T03:07:02.402835",
    "pair": "DOT-USD",
    "old_signal": "HOLD",
    "new_signal": "SHORT"
  },
  {
    "time": "2026-06-06T03:07:02.402839",
    "pair": "NEAR-USD",
    "old_signal": "HOLD",
    "new_signal": "SHORT"
  },
  {
    "time": "2026-06-06T03:22:06.394772",
    "pair": "ETH-USD",
    "old_signal": "HOLD",
    "new_signal": "STRONG_SHORT"
  },
  {
    "time": "2026-06-06T03:22:06.394782",
    "pair": "LTC-USD",
    "old_signal": "HOLD",
    "new_signal": "STRONG_SHORT"
  },
  {
    "time": "2026-06-06T03:22:06.394787",
    "pair": "XRP-USD",
    "old_signal": "HOLD",
    "new_signal": "SHORT"
  },
  {
    "time": "2026-06-06T03:22:06.394791",
    "pair": "BTC-USD",
    "old_signal": "HOLD",
    "new_signal": "SHORT"
  },
  {
    "time": "2026-06-06T03:22:06.394795",
    "pair": "DOT-USD",
    "old_signal": "SHORT",
    "new_signal": "HOLD"
  },
  {
    "time": "2026-06-06T03:37:10.392600",
    "pair": "NEAR-USD",
    "old_signal": "SHORT",
    "new_signal": "STRONG_SHORT"
  },
  {
    "time": "2026-06-06T03:37:10.392610",
    "pair": "BTC-USD",
    "old_signal": "SHORT",
    "new_signal": "STRONG_SHORT"
  },
  {
    "time": "2026-06-06T03:37:10.392614",
    "pair": "DOT-USD",
    "old_signal": "HOLD",
    "new_signal": "STRONG_SHORT"
  },
  {
    "time": "2026-06-06T03:37:10.392617",
    "pair": "SOL-USD",
    "old_signal": "HOLD",
    "new_signal": "STRONG_SHORT"
  },
  {
    "time": "2026-06-06T03:37:10.392621",
    "pair": "LINK-USD",
    "old_signal": "HOLD",
    "new_signal": "STRONG_SHORT"
  },
  {
    "time": "2026-06-06T03:37:10.392625",
    "pair": "AAVE-USD",
    "old_signal": "STRONG_SHORT",
    "new_signal": "SHORT"
  },
  {
    "time": "2026-06-06T03:37:10.392629",
    "pair": "DOGE-USD",
    "old_signal": "HOLD",
    "new_signal": "SHORT"
  },
  {
    "time": "2026-06-06T03:52:14.393255",
    "pair": "NEAR-USD",
    "old_signal": "STRONG_SHORT",
    "new_signal": "SHORT"
  },
  {
    "time": "2026-06-06T03:52:14.393264",
    "pair": "BTC-USD",
    "old_signal": "STRONG_SHORT",
    "new_signal": "SHORT"
  },
  {
    "time": "2026-06-06T03:52:14.393268",
    "pair": "DOT-USD",
    "old_signal": "STRONG_SHORT",
    "new_signal": "SHORT"
  },
  {
    "time": "2026-06-06T03:52:14.393272",
    "pair": "DOGE-USD",
    "old_signal": "SHORT",
    "new_signal": "HOLD"
  },
  {
    "time": "2026-06-06T04:07:18.599989",
    "pair": "NEAR-USD",
    "old_signal": "SHORT",
    "new_signal": "STRONG_SHORT"
  },
  {
    "time": "2026-06-06T04:07:18.599998",
    "pair": "BTC-USD",
    "old_signal": "SHORT",
    "new_signal": "STRONG_SHORT"
  },
  {
    "time": "2026-06-06T04:07:18.600004",
    "pair": "DOGE-USD",
    "old_signal": "HOLD",
    "new_signal": "SHORT"
  },
  {
    "time": "2026-06-06T04:07:18.600008",
    "pair": "ETH-USD",
    "old_signal": "STRONG_SHORT",
    "new_signal": "SHORT"
  },
  {
    "time": "2026-06-06T04:07:18.600012",
    "pair": "SOL-USD",
    "old_signal": "STRONG_SHORT",
    "new_signal": "SHORT"
  },
  {
    "time": "2026-06-06T04:22:22.797092",
    "pair": "AAVE-USD",
    "old_signal": "SHORT",
    "new_signal": "STRONG_SHORT"
  },
  {
    "time": "2026-06-06T04:22:22.797101",
    "pair": "DOT-USD",
    "old_signal": "SHORT",
    "new_signal": "STRONG_SHORT"
  },
  {
    "time": "2026-06-06T04:22:22.797105",
    "pair": "SOL-USD",
    "old_signal": "SHORT",
    "new_signal": "STRONG_SHORT"
  },
  {
    "time": "2026-06-06T04:22:22.797110",
    "pair": "DOGE-USD",
    "old_signal": "SHORT",
    "new_signal": "STRONG_SHORT"
  },
  {
    "time": "2026-06-06T04:22:22.797113",
    "pair": "INJ-USD",
    "old_signal": "HOLD",
    "new_signal": "STRONG_SHORT"
  },
  {
    "time": "2026-06-06T04:22:22.797117",
    "pair": "ETH-USD",
    "old_signal": "SHORT",
    "new_signal": "STRONG_SHORT"
  },
  {
    "time": "2026-06-06T04:52:31.151109",
    "pair": "BTC-USD",
    "old_signal": "STRONG_SHORT",
    "new_signal": "SHORT"
  },
  {
    "time": "2026-06-06T04:52:31.151118",
    "pair": "AAVE-USD",
    "old_signal": "STRONG_SHORT",
    "new_signal": "SHORT"
  },
  {
    "time": "2026-06-06T04:52:31.151121",
    "pair": "DOT-USD",
    "old_signal": "STRONG_SHORT",
    "new_signal": "SHORT"
  },
  {
    "time": "2026-06-06T04:52:31.151125",
    "pair": "AVAX-USD",
    "old_signal": "STRONG_SHORT",
    "new_signal": "SHORT"
  },
  {
    "time": "2026-06-06T04:52:31.151128",
    "pair": "LINK-USD",
    "old_signal": "STRONG_SHORT",
    "new_signal": "SHORT"
  },
  {
    "time": "2026-06-06T04:52:31.151132",
    "pair": "XRP-USD",
    "old_signal": "SHORT",
    "new_signal": "HOLD"
  },
  {
    "time": "2026-06-06T04:52:31.151135",
    "pair": "DOGE-USD",
    "old_signal": "STRONG_SHORT",
    "new_signal": "HOLD"
  }
]