[
  {
    "time": "2026-05-31T17:01:31.151581",
    "pair": "ICP-USD",
    "old_signal": "STRONG_SHORT",
    "new_signal": "SHORT"
  },
  {
    "time": "2026-05-31T17:01:31.151585",
    "pair": "OP-USD",
    "old_signal": "STRONG_SHORT",
    "new_signal": "SHORT"
  },
  {
    "time": "2026-05-31T17:01:31.151589",
    "pair": "SEI-USD",
    "old_signal": "STRONG_SHORT",
    "new_signal": "HOLD"
  },
  {
    "time": "2026-05-31T17:01:31.151593",
    "pair": "INJ-USD",
    "old_signal": "SHORT",
    "new_signal": "HOLD"
  },
  {
    "time": "2026-05-31T17:16:39.341532",
    "pair": "DOGE-USD",
    "old_signal": "SHORT",
    "new_signal": "STRONG_SHORT"
  },
  {
    "time": "2026-05-31T17:16:39.341542",
    "pair": "INJ-USD",
    "old_signal": "HOLD",
    "new_signal": "STRONG_SHORT"
  },
  {
    "time": "2026-05-31T17:16:39.341546",
    "pair": "ICP-USD",
    "old_signal": "SHORT",
    "new_signal": "STRONG_SHORT"
  },
  {
    "time": "2026-05-31T17:16:39.341549",
    "pair": "NEAR-USD",
    "old_signal": "STRONG_SHORT",
    "new_signal": "SHORT"
  },
  {
    "time": "2026-05-31T17:16:39.341553",
    "pair": "SHIB-USD",
    "old_signal": "STRONG_SHORT",
    "new_signal": "SHORT"
  },
  {
    "time": "2026-05-31T17:16:39.341559",
    "pair": "LINK-USD",
    "old_signal": "STRONG_SHORT",
    "new_signal": "SHORT"
  },
  {
    "time": "2026-05-31T17:16:39.341563",
    "pair": "LTC-USD",
    "old_signal": "STRONG_SHORT",
    "new_signal": "SHORT"
  },
  {
    "time": "2026-05-31T17:16:39.341567",
    "pair": "UNI-USD",
    "old_signal": "STRONG_SHORT",
    "new_signal": "SHORT"
  },
  {
    "time": "2026-05-31T17:16:39.341570",
    "pair": "AAVE-USD",
    "old_signal": "STRONG_SHORT",
    "new_signal": "SHORT"
  },
  {
    "time": "2026-05-31T17:31:47.442296",
    "pair": "INJ-USD",
    "old_signal": "STRONG_SHORT",
    "new_signal": "SHORT"
  },
  {
    "time": "2026-05-31T17:31:47.442304",
    "pair": "FET-USD",
    "old_signal": "STRONG_SHORT",
    "new_signal": "SHORT"
  },
  {
    "time": "2026-05-31T17:31:47.442308",
    "pair": "ETH-USD",
    "old_signal": "STRONG_SHORT",
    "new_signal": "SHORT"
  },
  {
    "time": "2026-05-31T17:31:47.442318",
    "pair": "ICP-USD",
    "old_signal": "STRONG_SHORT",
    "new_signal": "SHORT"
  },
  {
    "time": "2026-05-31T17:31:47.442324",
    "pair": "DOGE-USD",
    "old_signal": "STRONG_SHORT",
    "new_signal": "HOLD"
  },
  {
    "time": "2026-05-31T17:46:55.030606",
    "pair": "MATIC-USD",
    "old_signal": "HOLD",
    "new_signal": "BUY"
  },
  {
    "time": "2026-05-31T17:46:55.030616",
    "pair": "FET-USD",
    "old_signal": "SHORT",
    "new_signal": "HOLD"
  },
  {
    "time": "2026-05-31T17:46:55.030620",
    "pair": "ETH-USD",
    "old_signal": "SHORT",
    "new_signal": "HOLD"
  },
  {
    "time": "2026-05-31T17:46:55.030623",
    "pair": "SHIB-USD",
    "old_signal": "SHORT",
    "new_signal": "HOLD"
  },
  {
    "time": "2026-05-31T17:46:55.030627",
    "pair": "BCH-USD",
    "old_signal": "SHORT",
    "new_signal": "HOLD"
  },
  {
    "time": "2026-05-31T17:46:55.030630",
    "pair": "FIL-USD",
    "old_signal": "SHORT",
    "new_signal": "HOLD"
  },
  {
    "time": "2026-05-31T17:46:55.030634",
    "pair": "SOL-USD",
    "old_signal": "SHORT",
    "new_signal": "HOLD"
  },
  {
    "time": "2026-05-31T17:46:55.030637",
    "pair": "ADA-USD",
    "old_signal": "SHORT",
    "new_signal": "HOLD"
  },
  {
    "time": "2026-05-31T17:46:55.030641",
    "pair": "AVAX-USD",
    "old_signal": "SHORT",
    "new_signal": "HOLD"
  },
  {
    "time": "2026-05-31T17:46:55.030646",
    "pair": "LINK-USD",
    "old_signal": "SHORT",
    "new_signal": "HOLD"
  },
  {
    "time": "2026-05-31T17:46:55.030649",
    "pair": "DOT-USD",
    "old_signal": "SHORT",
    "new_signal": "HOLD"
  },
  {
    "time": "2026-05-31T17:46:55.030653",
    "pair": "UNI-USD",
    "old_signal": "SHORT",
    "new_signal": "HOLD"
  },
  {
    "time": "2026-05-31T17:46:55.030656",
    "pair": "AAVE-USD",
    "old_signal": "SHORT",
    "new_signal": "HOLD"
  },
  {
    "time": "2026-05-31T17:46:55.030660",
    "pair": "ATOM-USD",
    "old_signal": "SHORT",
    "new_signal": "HOLD"
  },
  {
    "time": "2026-05-31T17:46:55.030663",
    "pair": "HBAR-USD",
    "old_signal": "SHORT",
    "new_signal": "HOLD"
  },
  {
    "time": "2026-05-31T17:46:55.030667",
    "pair": "ICP-USD",
    "old_signal": "SHORT",
    "new_signal": "HOLD"
  },
  {
    "time": "2026-05-31T17:46:55.030670",
    "pair": "APT-USD",
    "old_signal": "SHORT",
    "new_signal": "HOLD"
  },
  {
    "time": "2026-05-31T17:46:55.030673",
    "pair": "OP-USD",
    "old_signal": "SHORT",
    "new_signal": "HOLD"
  },
  {
    "time": "2026-05-31T17:46:55.030677",
    "pair": "SUI-USD",
    "old_signal": "SHORT",
    "new_signal": "HOLD"
  },
  {
    "time": "2026-05-31T17:46:55.030682",
    "pair": "INJ-USD",
    "old_signal": "SHORT",
    "new_signal": "HOLD"
  },
  {
    "time": "2026-05-31T17:46:55.030686",
    "pair": "BTC-USD",
    "old_signal": "SHORT",
    "new_signal": "HOLD"
  },
  {
    "time": "2026-05-31T17:46:55.030690",
    "pair": "ETC-USD",
    "old_signal": "SHORT",
    "new_signal": "HOLD"
  },
  {
    "time": "2026-05-31T17:46:55.030693",
    "pair": "ARB-USD",
    "old_signal": "SHORT",
    "new_signal": "HOLD"
  },
  {
    "time": "2026-05-31T18:02:03.139455",
    "pair": "ATOM-USD",
    "old_signal": "HOLD",
    "new_signal": "SHORT"
  },
  {
    "time": "2026-05-31T18:02:03.139473",
    "pair": "LTC-USD",
    "old_signal": "SHORT",
    "new_signal": "HOLD"
  },
  {
    "time": "2026-05-31T18:02:03.139479",
    "pair": "NEAR-USD",
    "old_signal": "SHORT",
    "new_signal": "HOLD"
  },
  {
    "time": "2026-05-31T18:17:11.271676",
    "pair": "NEAR-USD",
    "old_signal": "HOLD",
    "new_signal": "SHORT"
  },
  {
    "time": "2026-05-31T18:17:11.271686",
    "pair": "FET-USD",
    "old_signal": "HOLD",
    "new_signal": "SHORT"
  },
  {
    "time": "2026-05-31T18:17:11.271690",
    "pair": "FIL-USD",
    "old_signal": "HOLD",
    "new_signal": "SHORT"
  },
  {
    "time": "2026-05-31T18:17:11.271694",
    "pair": "LINK-USD",
    "old_signal": "HOLD",
    "new_signal": "SHORT"
  },
  {
    "time": "2026-05-31T18:17:11.271698",
    "pair": "DOT-USD",
    "old_signal": "HOLD",
    "new_signal": "SHORT"
  },
  {
    "time": "2026-05-31T18:17:11.271701",
    "pair": "LTC-USD",
    "old_signal": "HOLD",
    "new_signal": "SHORT"
  },
  {
    "time": "2026-05-31T18:17:11.271704",
    "pair": "OP-USD",
    "old_signal": "HOLD",
    "new_signal": "SHORT"
  },
  {
    "time": "2026-05-31T18:17:11.271711",
    "pair": "MATIC-USD",
    "old_signal": "BUY",
    "new_signal": "HOLD"
  },
  {
    "time": "2026-05-31T18:32:19.619718",
    "pair": "NEAR-USD",
    "old_signal": "SHORT",
    "new_signal": "STRONG_SHORT"
  },
  {
    "time": "2026-05-31T18:32:19.619730",
    "pair": "AAVE-USD",
    "old_signal": "HOLD",
    "new_signal": "SHORT"
  },
  {
    "time": "2026-05-31T18:32:19.619738",
    "pair": "FET-USD",
    "old_signal": "SHORT",
    "new_signal": "HOLD"
  },
  {
    "time": "2026-05-31T18:32:19.619745",
    "pair": "LINK-USD",
    "old_signal": "SHORT",
    "new_signal": "HOLD"
  },
  {
    "time": "2026-05-31T18:47:28.340093",
    "pair": "FET-USD",
    "old_signal": "HOLD",
    "new_signal": "STRONG_SHORT"
  },
  {
    "time": "2026-05-31T18:47:28.340103",
    "pair": "BTC-USD",
    "old_signal": "HOLD",
    "new_signal": "SHORT"
  },
  {
    "time": "2026-05-31T18:47:28.340106",
    "pair": "NEAR-USD",
    "old_signal": "STRONG_SHORT",
    "new_signal": "SHORT"
  },
  {
    "time": "2026-05-31T18:47:28.340113",
    "pair": "FIL-USD",
    "old_signal": "SHORT",
    "new_signal": "HOLD"
  },
  {
    "time": "2026-05-31T18:47:28.340118",
    "pair": "DOT-USD",
    "old_signal": "SHORT",
    "new_signal": "HOLD"
  },
  {
    "time": "2026-05-31T18:47:28.340123",
    "pair": "AAVE-USD",
    "old_signal": "SHORT",
    "new_signal": "HOLD"
  },
  {
    "time": "2026-05-31T18:47:28.340127",
    "pair": "ATOM-USD",
    "old_signal": "SHORT",
    "new_signal": "HOLD"
  },
  {
    "time": "2026-05-31T19:02:36.756653",
    "pair": "ETH-USD",
    "old_signal": "HOLD",
    "new_signal": "SHORT"
  },
  {
    "time": "2026-05-31T19:02:36.756665",
    "pair": "BTC-USD",
    "old_signal": "SHORT",
    "new_signal": "HOLD"
  },
  {
    "time": "2026-05-31T19:02:36.756672",
    "pair": "LTC-USD",
    "old_signal": "SHORT",
    "new_signal": "HOLD"
  },
  {
    "time": "2026-05-31T19:02:36.756681",
    "pair": "FET-USD",
    "old_signal": "STRONG_SHORT",
    "new_signal": "HOLD"
  },
  {
    "time": "2026-05-31T19:17:45.318546",
    "pair": "FIL-USD",
    "old_signal": "HOLD",
    "new_signal": "STRONG_SHORT"
  },
  {
    "time": "2026-05-31T19:17:45.318557",
    "pair": "OP-USD",
    "old_signal": "SHORT",
    "new_signal": "STRONG_SHORT"
  },
  {
    "time": "2026-05-31T19:17:45.318561",
    "pair": "XRP-USD",
    "old_signal": "HOLD",
    "new_signal": "SHORT"
  },
  {
    "time": "2026-05-31T19:17:45.318565",
    "pair": "AVAX-USD",
    "old_signal": "HOLD",
    "new_signal": "SHORT"
  },
  {
    "time": "2026-05-31T19:17:45.318580",
    "pair": "ETC-USD",
    "old_signal": "HOLD",
    "new_signal": "SHORT"
  },
  {
    "time": "2026-05-31T19:32:53.429024",
    "pair": "ETH-USD",
    "old_signal": "SHORT",
    "new_signal": "STRONG_SHORT"
  },
  {
    "time": "2026-05-31T19:32:53.429039",
    "pair": "LINK-USD",
    "old_signal": "HOLD",
    "new_signal": "SHORT"
  },
  {
    "time": "2026-05-31T19:32:53.429043",
    "pair": "APT-USD",
    "old_signal": "HOLD",
    "new_signal": "SHORT"
  },
  {
    "time": "2026-05-31T19:32:53.429047",
    "pair": "BTC-USD",
    "old_signal": "HOLD",
    "new_signal": "SHORT"
  },
  {
    "time": "2026-05-31T19:32:53.429059",
    "pair": "ETC-USD",
    "old_signal": "SHORT",
    "new_signal": "HOLD"
  },
  {
    "time": "2026-05-31T19:48:01.643068",
    "pair": "BTC-USD",
    "old_signal": "SHORT",
    "new_signal": "STRONG_SHORT"
  },
  {
    "time": "2026-05-31T19:48:01.643078",
    "pair": "ETH-USD",
    "old_signal": "STRONG_SHORT",
    "new_signal": "SHORT"
  },
  {
    "time": "2026-05-31T19:48:01.643082",
    "pair": "FIL-USD",
    "old_signal": "STRONG_SHORT",
    "new_signal": "SHORT"
  },
  {
    "time": "2026-05-31T19:48:01.643086",
    "pair": "OP-USD",
    "old_signal": "STRONG_SHORT",
    "new_signal": "SHORT"
  },
  {
    "time": "2026-05-31T19:48:01.643090",
    "pair": "AVAX-USD",
    "old_signal": "SHORT",
    "new_signal": "HOLD"
  },
  {
    "time": "2026-05-31T19:48:01.643094",
    "pair": "XRP-USD",
    "old_signal": "SHORT",
    "new_signal": "HOLD"
  },
  {
    "time": "2026-05-31T19:48:01.643099",
    "pair": "LINK-USD",
    "old_signal": "SHORT",
    "new_signal": "HOLD"
  },
  {
    "time": "2026-05-31T19:48:01.643106",
    "pair": "APT-USD",
    "old_signal": "SHORT",
    "new_signal": "HOLD"
  },
  {
    "time": "2026-05-31T20:03:09.984982",
    "pair": "MATIC-USD",
    "old_signal": "HOLD",
    "new_signal": "BUY"
  },
  {
    "time": "2026-05-31T20:03:09.984991",
    "pair": "FIL-USD",
    "old_signal": "SHORT",
    "new_signal": "HOLD"
  },
  {
    "time": "2026-05-31T20:03:09.984996",
    "pair": "NEAR-USD",
    "old_signal": "SHORT",
    "new_signal": "HOLD"
  },
  {
    "time": "2026-05-31T20:03:09.985002",
    "pair": "OP-USD",
    "old_signal": "SHORT",
    "new_signal": "HOLD"
  },
  {
    "time": "2026-05-31T20:03:09.985006",
    "pair": "ETH-USD",
    "old_signal": "SHORT",
    "new_signal": "HOLD"
  },
  {
    "time": "2026-05-31T20:03:09.985016",
    "pair": "BTC-USD",
    "old_signal": "STRONG_SHORT",
    "new_signal": "HOLD"
  },
  {
    "time": "2026-05-31T20:33:27.137558",
    "pair": "FET-USD",
    "old_signal": "HOLD",
    "new_signal": "BUY"
  },
  {
    "time": "2026-05-31T21:03:42.827600",
    "pair": "FET-USD",
    "old_signal": "BUY",
    "new_signal": "HOLD"
  },
  {
    "time": "2026-05-31T21:33:58.613336",
    "pair": "MATIC-USD",
    "old_signal": "BUY",
    "new_signal": "HOLD"
  },
  {
    "time": "2026-05-31T21:49:07.976936",
    "pair": "MATIC-USD",
    "old_signal": "HOLD",
    "new_signal": "BUY"
  },
  {
    "time": "2026-05-31T21:49:07.976944",
    "pair": "NEAR-USD",
    "old_signal": "HOLD",
    "new_signal": "BUY"
  },
  {
    "time": "2026-05-31T22:04:16.445495",
    "pair": "FET-USD",
    "old_signal": "HOLD",
    "new_signal": "BUY"
  },
  {
    "time": "2026-05-31T22:04:16.445513",
    "pair": "NEAR-USD",
    "old_signal": "BUY",
    "new_signal": "HOLD"
  },
  {
    "time": "2026-05-31T22:34:33.184177",
    "pair": "FET-USD",
    "old_signal": "BUY",
    "new_signal": "HOLD"
  },
  {
    "time": "2026-05-31T23:04:49.439494",
    "pair": "SHIB-USD",
    "old_signal": "HOLD",
    "new_signal": "BUY"
  }
]