[
  {
    "time": "2026-06-02T06:52:35.457328",
    "pair": "ETH-USD",
    "old_signal": "SHORT",
    "new_signal": "STRONG_SHORT"
  },
  {
    "time": "2026-06-02T06:52:35.457332",
    "pair": "ATOM-USD",
    "old_signal": "SHORT",
    "new_signal": "STRONG_SHORT"
  },
  {
    "time": "2026-06-02T06:52:35.457336",
    "pair": "SEI-USD",
    "old_signal": "HOLD",
    "new_signal": "SHORT"
  },
  {
    "time": "2026-06-02T06:52:35.457339",
    "pair": "DOGE-USD",
    "old_signal": "HOLD",
    "new_signal": "SHORT"
  },
  {
    "time": "2026-06-02T06:52:35.457343",
    "pair": "DOT-USD",
    "old_signal": "STRONG_SHORT",
    "new_signal": "SHORT"
  },
  {
    "time": "2026-06-02T06:52:35.457346",
    "pair": "FET-USD",
    "old_signal": "HOLD",
    "new_signal": "SHORT"
  },
  {
    "time": "2026-06-02T06:52:35.457351",
    "pair": "BCH-USD",
    "old_signal": "STRONG_SHORT",
    "new_signal": "SHORT"
  },
  {
    "time": "2026-06-02T07:07:43.537939",
    "pair": "ICP-USD",
    "old_signal": "HOLD",
    "new_signal": "STRONG_SHORT"
  },
  {
    "time": "2026-06-02T07:07:43.537948",
    "pair": "ARB-USD",
    "old_signal": "SHORT",
    "new_signal": "STRONG_SHORT"
  },
  {
    "time": "2026-06-02T07:07:43.537954",
    "pair": "DOT-USD",
    "old_signal": "SHORT",
    "new_signal": "STRONG_SHORT"
  },
  {
    "time": "2026-06-02T07:07:43.537957",
    "pair": "SHIB-USD",
    "old_signal": "SHORT",
    "new_signal": "STRONG_SHORT"
  },
  {
    "time": "2026-06-02T07:07:43.537961",
    "pair": "BCH-USD",
    "old_signal": "SHORT",
    "new_signal": "STRONG_SHORT"
  },
  {
    "time": "2026-06-02T07:07:43.537965",
    "pair": "SOL-USD",
    "old_signal": "SHORT",
    "new_signal": "STRONG_SHORT"
  },
  {
    "time": "2026-06-02T07:07:43.537969",
    "pair": "ADA-USD",
    "old_signal": "SHORT",
    "new_signal": "STRONG_SHORT"
  },
  {
    "time": "2026-06-02T07:07:43.537973",
    "pair": "LINK-USD",
    "old_signal": "SHORT",
    "new_signal": "STRONG_SHORT"
  },
  {
    "time": "2026-06-02T07:07:43.537976",
    "pair": "UNI-USD",
    "old_signal": "SHORT",
    "new_signal": "STRONG_SHORT"
  },
  {
    "time": "2026-06-02T07:07:43.537981",
    "pair": "ETC-USD",
    "old_signal": "SHORT",
    "new_signal": "STRONG_SHORT"
  },
  {
    "time": "2026-06-02T07:07:43.537985",
    "pair": "HBAR-USD",
    "old_signal": "SHORT",
    "new_signal": "STRONG_SHORT"
  },
  {
    "time": "2026-06-02T07:07:43.537989",
    "pair": "SUI-USD",
    "old_signal": "SHORT",
    "new_signal": "STRONG_SHORT"
  },
  {
    "time": "2026-06-02T07:07:43.537993",
    "pair": "XRP-USD",
    "old_signal": "HOLD",
    "new_signal": "SHORT"
  },
  {
    "time": "2026-06-02T07:07:43.537997",
    "pair": "GRT-USD",
    "old_signal": "HOLD",
    "new_signal": "SHORT"
  },
  {
    "time": "2026-06-02T07:07:43.538005",
    "pair": "FET-USD",
    "old_signal": "SHORT",
    "new_signal": "HOLD"
  },
  {
    "time": "2026-06-02T07:22:52.110396",
    "pair": "INJ-USD",
    "old_signal": "HOLD",
    "new_signal": "BUY"
  },
  {
    "time": "2026-06-02T07:22:52.110406",
    "pair": "FET-USD",
    "old_signal": "HOLD",
    "new_signal": "BUY"
  },
  {
    "time": "2026-06-02T07:22:52.110410",
    "pair": "BTC-USD",
    "old_signal": "STRONG_SHORT",
    "new_signal": "SHORT"
  },
  {
    "time": "2026-06-02T07:22:52.110414",
    "pair": "ETH-USD",
    "old_signal": "STRONG_SHORT",
    "new_signal": "SHORT"
  },
  {
    "time": "2026-06-02T07:22:52.110417",
    "pair": "DOT-USD",
    "old_signal": "STRONG_SHORT",
    "new_signal": "SHORT"
  },
  {
    "time": "2026-06-02T07:22:52.110421",
    "pair": "SHIB-USD",
    "old_signal": "STRONG_SHORT",
    "new_signal": "SHORT"
  },
  {
    "time": "2026-06-02T07:22:52.110426",
    "pair": "ICP-USD",
    "old_signal": "STRONG_SHORT",
    "new_signal": "BUY"
  },
  {
    "time": "2026-06-02T07:22:52.110429",
    "pair": "SOL-USD",
    "old_signal": "STRONG_SHORT",
    "new_signal": "SHORT"
  },
  {
    "time": "2026-06-02T07:22:52.110433",
    "pair": "ADA-USD",
    "old_signal": "STRONG_SHORT",
    "new_signal": "SHORT"
  },
  {
    "time": "2026-06-02T07:22:52.110438",
    "pair": "LINK-USD",
    "old_signal": "STRONG_SHORT",
    "new_signal": "SHORT"
  },
  {
    "time": "2026-06-02T07:22:52.110442",
    "pair": "UNI-USD",
    "old_signal": "STRONG_SHORT",
    "new_signal": "SHORT"
  },
  {
    "time": "2026-06-02T07:22:52.110446",
    "pair": "AAVE-USD",
    "old_signal": "STRONG_SHORT",
    "new_signal": "SHORT"
  },
  {
    "time": "2026-06-02T07:22:52.110449",
    "pair": "ATOM-USD",
    "old_signal": "STRONG_SHORT",
    "new_signal": "SHORT"
  },
  {
    "time": "2026-06-02T07:22:52.110453",
    "pair": "ETC-USD",
    "old_signal": "STRONG_SHORT",
    "new_signal": "SHORT"
  },
  {
    "time": "2026-06-02T07:22:52.110456",
    "pair": "HBAR-USD",
    "old_signal": "STRONG_SHORT",
    "new_signal": "SHORT"
  },
  {
    "time": "2026-06-02T07:22:52.110459",
    "pair": "APT-USD",
    "old_signal": "STRONG_SHORT",
    "new_signal": "SHORT"
  },
  {
    "time": "2026-06-02T07:22:52.110463",
    "pair": "ARB-USD",
    "old_signal": "STRONG_SHORT",
    "new_signal": "SHORT"
  },
  {
    "time": "2026-06-02T07:22:52.110466",
    "pair": "SUI-USD",
    "old_signal": "STRONG_SHORT",
    "new_signal": "SHORT"
  },
  {
    "time": "2026-06-02T07:22:52.110470",
    "pair": "XRP-USD",
    "old_signal": "SHORT",
    "new_signal": "HOLD"
  },
  {
    "time": "2026-06-02T07:22:52.110474",
    "pair": "DOGE-USD",
    "old_signal": "SHORT",
    "new_signal": "HOLD"
  },
  {
    "time": "2026-06-02T07:22:52.110478",
    "pair": "SEI-USD",
    "old_signal": "SHORT",
    "new_signal": "HOLD"
  },
  {
    "time": "2026-06-02T07:22:52.110481",
    "pair": "GRT-USD",
    "old_signal": "SHORT",
    "new_signal": "HOLD"
  },
  {
    "time": "2026-06-02T07:22:52.110485",
    "pair": "BCH-USD",
    "old_signal": "STRONG_SHORT",
    "new_signal": "HOLD"
  },
  {
    "time": "2026-06-02T07:22:52.110488",
    "pair": "LTC-USD",
    "old_signal": "SHORT",
    "new_signal": "HOLD"
  },
  {
    "time": "2026-06-02T07:38:00.759044",
    "pair": "BCH-USD",
    "old_signal": "HOLD",
    "new_signal": "SHORT"
  },
  {
    "time": "2026-06-02T07:38:00.759066",
    "pair": "SHIB-USD",
    "old_signal": "SHORT",
    "new_signal": "HOLD"
  },
  {
    "time": "2026-06-02T07:53:09.522410",
    "pair": "FET-USD",
    "old_signal": "BUY",
    "new_signal": "STRONG_BUY"
  },
  {
    "time": "2026-06-02T07:53:09.522441",
    "pair": "ADA-USD",
    "old_signal": "SHORT",
    "new_signal": "HOLD"
  },
  {
    "time": "2026-06-02T08:08:17.442078",
    "pair": "XRP-USD",
    "old_signal": "HOLD",
    "new_signal": "SHORT"
  },
  {
    "time": "2026-06-02T08:08:17.442095",
    "pair": "SHIB-USD",
    "old_signal": "HOLD",
    "new_signal": "SHORT"
  },
  {
    "time": "2026-06-02T08:08:17.442108",
    "pair": "FET-USD",
    "old_signal": "STRONG_BUY",
    "new_signal": "HOLD"
  },
  {
    "time": "2026-06-02T08:23:25.817654",
    "pair": "DOT-USD",
    "old_signal": "SHORT",
    "new_signal": "HOLD"
  },
  {
    "time": "2026-06-02T08:23:25.817667",
    "pair": "FIL-USD",
    "old_signal": "SHORT",
    "new_signal": "HOLD"
  },
  {
    "time": "2026-06-02T08:23:25.817670",
    "pair": "ICP-USD",
    "old_signal": "BUY",
    "new_signal": "HOLD"
  },
  {
    "time": "2026-06-02T08:23:25.817676",
    "pair": "ATOM-USD",
    "old_signal": "SHORT",
    "new_signal": "HOLD"
  },
  {
    "time": "2026-06-02T08:23:25.817680",
    "pair": "ETC-USD",
    "old_signal": "SHORT",
    "new_signal": "HOLD"
  },
  {
    "time": "2026-06-02T08:23:25.817684",
    "pair": "XRP-USD",
    "old_signal": "SHORT",
    "new_signal": "HOLD"
  },
  {
    "time": "2026-06-02T08:23:25.817689",
    "pair": "SHIB-USD",
    "old_signal": "SHORT",
    "new_signal": "HOLD"
  },
  {
    "time": "2026-06-02T08:38:34.029953",
    "pair": "BCH-USD",
    "old_signal": "SHORT",
    "new_signal": "STRONG_SHORT"
  },
  {
    "time": "2026-06-02T08:38:34.029967",
    "pair": "FET-USD",
    "old_signal": "HOLD",
    "new_signal": "BUY"
  },
  {
    "time": "2026-06-02T08:38:34.029972",
    "pair": "SHIB-USD",
    "old_signal": "HOLD",
    "new_signal": "SHORT"
  },
  {
    "time": "2026-06-02T08:38:34.029982",
    "pair": "SOL-USD",
    "old_signal": "SHORT",
    "new_signal": "HOLD"
  },
  {
    "time": "2026-06-02T08:38:34.029986",
    "pair": "AVAX-USD",
    "old_signal": "SHORT",
    "new_signal": "HOLD"
  },
  {
    "time": "2026-06-02T08:38:34.029991",
    "pair": "UNI-USD",
    "old_signal": "SHORT",
    "new_signal": "HOLD"
  },
  {
    "time": "2026-06-02T08:38:34.029995",
    "pair": "HBAR-USD",
    "old_signal": "SHORT",
    "new_signal": "HOLD"
  },
  {
    "time": "2026-06-02T08:53:41.930513",
    "pair": "SUI-USD",
    "old_signal": "SHORT",
    "new_signal": "STRONG_SHORT"
  },
  {
    "time": "2026-06-02T08:53:41.930528",
    "pair": "BTC-USD",
    "old_signal": "SHORT",
    "new_signal": "STRONG_SHORT"
  },
  {
    "time": "2026-06-02T08:53:41.930533",
    "pair": "ETH-USD",
    "old_signal": "SHORT",
    "new_signal": "STRONG_SHORT"
  },
  {
    "time": "2026-06-02T08:53:41.930537",
    "pair": "SOL-USD",
    "old_signal": "HOLD",
    "new_signal": "STRONG_SHORT"
  },
  {
    "time": "2026-06-02T08:53:41.930542",
    "pair": "XRP-USD",
    "old_signal": "HOLD",
    "new_signal": "SHORT"
  },
  {
    "time": "2026-06-02T08:53:41.930546",
    "pair": "GRT-USD",
    "old_signal": "HOLD",
    "new_signal": "SHORT"
  },
  {
    "time": "2026-06-02T08:53:41.930550",
    "pair": "BCH-USD",
    "old_signal": "STRONG_SHORT",
    "new_signal": "SHORT"
  },
  {
    "time": "2026-06-02T08:53:41.930554",
    "pair": "HBAR-USD",
    "old_signal": "HOLD",
    "new_signal": "SHORT"
  },
  {
    "time": "2026-06-02T08:53:41.930560",
    "pair": "INJ-USD",
    "old_signal": "BUY",
    "new_signal": "HOLD"
  },
  {
    "time": "2026-06-02T08:53:41.930565",
    "pair": "FET-USD",
    "old_signal": "BUY",
    "new_signal": "HOLD"
  },
  {
    "time": "2026-06-02T08:53:41.930571",
    "pair": "SHIB-USD",
    "old_signal": "SHORT",
    "new_signal": "HOLD"
  },
  {
    "time": "2026-06-02T08:53:41.930577",
    "pair": "APT-USD",
    "old_signal": "SHORT",
    "new_signal": "HOLD"
  },
  {
    "time": "2026-06-02T09:08:50.526501",
    "pair": "ETC-USD",
    "old_signal": "HOLD",
    "new_signal": "STRONG_SHORT"
  },
  {
    "time": "2026-06-02T09:08:50.526511",
    "pair": "SEI-USD",
    "old_signal": "HOLD",
    "new_signal": "SHORT"
  },
  {
    "time": "2026-06-02T09:08:50.526516",
    "pair": "NEAR-USD",
    "old_signal": "HOLD",
    "new_signal": "BUY"
  },
  {
    "time": "2026-06-02T09:08:50.526519",
    "pair": "SHIB-USD",
    "old_signal": "HOLD",
    "new_signal": "SHORT"
  },
  {
    "time": "2026-06-02T09:08:50.526524",
    "pair": "SOL-USD",
    "old_signal": "STRONG_SHORT",
    "new_signal": "HOLD"
  },
  {
    "time": "2026-06-02T09:08:50.526532",
    "pair": "AAVE-USD",
    "old_signal": "SHORT",
    "new_signal": "HOLD"
  },
  {
    "time": "2026-06-02T09:08:50.526536",
    "pair": "HBAR-USD",
    "old_signal": "SHORT",
    "new_signal": "HOLD"
  },
  {
    "time": "2026-06-02T09:23:58.990942",
    "pair": "SHIB-USD",
    "old_signal": "SHORT",
    "new_signal": "STRONG_SHORT"
  },
  {
    "time": "2026-06-02T09:23:58.990951",
    "pair": "SOL-USD",
    "old_signal": "HOLD",
    "new_signal": "STRONG_SHORT"
  },
  {
    "time": "2026-06-02T09:23:58.990955",
    "pair": "AVAX-USD",
    "old_signal": "HOLD",
    "new_signal": "STRONG_SHORT"
  },
  {
    "time": "2026-06-02T09:23:58.990959",
    "pair": "LINK-USD",
    "old_signal": "SHORT",
    "new_signal": "STRONG_SHORT"
  },
  {
    "time": "2026-06-02T09:23:58.990963",
    "pair": "ATOM-USD",
    "old_signal": "HOLD",
    "new_signal": "STRONG_SHORT"
  },
  {
    "time": "2026-06-02T09:23:58.990968",
    "pair": "INJ-USD",
    "old_signal": "HOLD",
    "new_signal": "BUY"
  },
  {
    "time": "2026-06-02T09:23:58.990972",
    "pair": "FET-USD",
    "old_signal": "HOLD",
    "new_signal": "SHORT"
  },
  {
    "time": "2026-06-02T09:23:58.990977",
    "pair": "UNI-USD",
    "old_signal": "HOLD",
    "new_signal": "SHORT"
  },
  {
    "time": "2026-06-02T09:23:58.990980",
    "pair": "AAVE-USD",
    "old_signal": "HOLD",
    "new_signal": "SHORT"
  },
  {
    "time": "2026-06-02T09:23:58.990984",
    "pair": "FIL-USD",
    "old_signal": "HOLD",
    "new_signal": "SHORT"
  },
  {
    "time": "2026-06-02T09:23:58.990988",
    "pair": "XRP-USD",
    "old_signal": "SHORT",
    "new_signal": "HOLD"
  },
  {
    "time": "2026-06-02T09:23:58.990992",
    "pair": "SEI-USD",
    "old_signal": "SHORT",
    "new_signal": "HOLD"
  },
  {
    "time": "2026-06-02T09:23:58.990996",
    "pair": "GRT-USD",
    "old_signal": "SHORT",
    "new_signal": "HOLD"
  },
  {
    "time": "2026-06-02T09:23:58.991004",
    "pair": "NEAR-USD",
    "old_signal": "BUY",
    "new_signal": "HOLD"
  }
]