[
  {
    "time": "2026-05-28T16:05:13.072751",
    "pair": "SEI-USD",
    "old_signal": "BUY",
    "new_signal": "HOLD"
  },
  {
    "time": "2026-05-28T16:20:22.250745",
    "pair": "AAVE-USD",
    "old_signal": "STRONG_SHORT",
    "new_signal": "SHORT"
  },
  {
    "time": "2026-05-28T16:20:22.250757",
    "pair": "NEAR-USD",
    "old_signal": "STRONG_SHORT",
    "new_signal": "HOLD"
  },
  {
    "time": "2026-05-28T16:20:22.250764",
    "pair": "BTC-USD",
    "old_signal": "STRONG_SHORT",
    "new_signal": "HOLD"
  },
  {
    "time": "2026-05-28T16:20:22.250769",
    "pair": "DOT-USD",
    "old_signal": "STRONG_SHORT",
    "new_signal": "HOLD"
  },
  {
    "time": "2026-05-28T16:35:31.164046",
    "pair": "MATIC-USD",
    "old_signal": "HOLD",
    "new_signal": "BUY"
  },
  {
    "time": "2026-05-28T16:35:31.164063",
    "pair": "AAVE-USD",
    "old_signal": "SHORT",
    "new_signal": "HOLD"
  },
  {
    "time": "2026-05-28T16:35:31.164071",
    "pair": "APT-USD",
    "old_signal": "STRONG_SHORT",
    "new_signal": "HOLD"
  },
  {
    "time": "2026-05-28T16:35:31.164076",
    "pair": "OP-USD",
    "old_signal": "SHORT",
    "new_signal": "HOLD"
  },
  {
    "time": "2026-05-28T16:50:40.259498",
    "pair": "SEI-USD",
    "old_signal": "HOLD",
    "new_signal": "STRONG_BUY"
  },
  {
    "time": "2026-05-28T17:05:49.344825",
    "pair": "HBAR-USD",
    "old_signal": "HOLD",
    "new_signal": "BUY"
  },
  {
    "time": "2026-05-28T17:20:58.387104",
    "pair": "HBAR-USD",
    "old_signal": "BUY",
    "new_signal": "STRONG_BUY"
  },
  {
    "time": "2026-05-28T17:20:58.387114",
    "pair": "ICP-USD",
    "old_signal": "HOLD",
    "new_signal": "BUY"
  },
  {
    "time": "2026-05-28T17:20:58.387118",
    "pair": "SEI-USD",
    "old_signal": "STRONG_BUY",
    "new_signal": "BUY"
  },
  {
    "time": "2026-05-28T17:20:58.387122",
    "pair": "INJ-USD",
    "old_signal": "HOLD",
    "new_signal": "BUY"
  },
  {
    "time": "2026-05-28T17:36:07.939142",
    "pair": "SEI-USD",
    "old_signal": "BUY",
    "new_signal": "STRONG_BUY"
  },
  {
    "time": "2026-05-28T17:36:07.939151",
    "pair": "HBAR-USD",
    "old_signal": "STRONG_BUY",
    "new_signal": "BUY"
  },
  {
    "time": "2026-05-28T17:36:07.939155",
    "pair": "AVAX-USD",
    "old_signal": "HOLD",
    "new_signal": "BUY"
  },
  {
    "time": "2026-05-28T17:36:07.939158",
    "pair": "ADA-USD",
    "old_signal": "HOLD",
    "new_signal": "BUY"
  },
  {
    "time": "2026-05-28T17:36:07.939162",
    "pair": "ICP-USD",
    "old_signal": "BUY",
    "new_signal": "HOLD"
  },
  {
    "time": "2026-05-28T17:36:07.939169",
    "pair": "INJ-USD",
    "old_signal": "BUY",
    "new_signal": "HOLD"
  },
  {
    "time": "2026-05-28T17:51:27.651520",
    "pair": "DOT-USD",
    "old_signal": "HOLD",
    "new_signal": "STRONG_BUY"
  },
  {
    "time": "2026-05-28T17:51:27.651529",
    "pair": "SEI-USD",
    "old_signal": "STRONG_BUY",
    "new_signal": "BUY"
  },
  {
    "time": "2026-05-28T17:51:27.651533",
    "pair": "FET-USD",
    "old_signal": "HOLD",
    "new_signal": "BUY"
  },
  {
    "time": "2026-05-28T17:51:27.651538",
    "pair": "SHIB-USD",
    "old_signal": "HOLD",
    "new_signal": "BUY"
  },
  {
    "time": "2026-05-28T18:06:36.181313",
    "pair": "HBAR-USD",
    "old_signal": "BUY",
    "new_signal": "STRONG_BUY"
  },
  {
    "time": "2026-05-28T18:06:36.181321",
    "pair": "ADA-USD",
    "old_signal": "BUY",
    "new_signal": "STRONG_BUY"
  },
  {
    "time": "2026-05-28T18:06:36.181327",
    "pair": "XRP-USD",
    "old_signal": "HOLD",
    "new_signal": "BUY"
  },
  {
    "time": "2026-05-28T18:06:36.181331",
    "pair": "DOT-USD",
    "old_signal": "STRONG_BUY",
    "new_signal": "BUY"
  },
  {
    "time": "2026-05-28T18:21:44.941345",
    "pair": "INJ-USD",
    "old_signal": "HOLD",
    "new_signal": "BUY"
  },
  {
    "time": "2026-05-28T18:21:44.941357",
    "pair": "ADA-USD",
    "old_signal": "STRONG_BUY",
    "new_signal": "HOLD"
  },
  {
    "time": "2026-05-28T18:21:44.941363",
    "pair": "SEI-USD",
    "old_signal": "BUY",
    "new_signal": "HOLD"
  },
  {
    "time": "2026-05-28T18:21:44.941368",
    "pair": "HBAR-USD",
    "old_signal": "STRONG_BUY",
    "new_signal": "HOLD"
  },
  {
    "time": "2026-05-28T18:36:53.651688",
    "pair": "SHIB-USD",
    "old_signal": "BUY",
    "new_signal": "HOLD"
  },
  {
    "time": "2026-05-28T18:36:53.651698",
    "pair": "FET-USD",
    "old_signal": "BUY",
    "new_signal": "HOLD"
  },
  {
    "time": "2026-05-28T18:36:53.651703",
    "pair": "XRP-USD",
    "old_signal": "BUY",
    "new_signal": "HOLD"
  },
  {
    "time": "2026-05-28T18:36:53.651706",
    "pair": "AVAX-USD",
    "old_signal": "BUY",
    "new_signal": "HOLD"
  },
  {
    "time": "2026-05-28T18:36:53.651710",
    "pair": "DOT-USD",
    "old_signal": "BUY",
    "new_signal": "HOLD"
  },
  {
    "time": "2026-05-28T18:52:02.655794",
    "pair": "SEI-USD",
    "old_signal": "HOLD",
    "new_signal": "BUY"
  },
  {
    "time": "2026-05-28T19:07:12.238895",
    "pair": "SHIB-USD",
    "old_signal": "HOLD",
    "new_signal": "STRONG_BUY"
  },
  {
    "time": "2026-05-28T19:07:12.238905",
    "pair": "FET-USD",
    "old_signal": "HOLD",
    "new_signal": "BUY"
  },
  {
    "time": "2026-05-28T19:07:12.238910",
    "pair": "AVAX-USD",
    "old_signal": "HOLD",
    "new_signal": "BUY"
  },
  {
    "time": "2026-05-28T19:07:12.238913",
    "pair": "ADA-USD",
    "old_signal": "HOLD",
    "new_signal": "BUY"
  },
  {
    "time": "2026-05-28T19:22:21.349884",
    "pair": "SHIB-USD",
    "old_signal": "STRONG_BUY",
    "new_signal": "BUY"
  },
  {
    "time": "2026-05-28T19:22:21.349893",
    "pair": "AVAX-USD",
    "old_signal": "BUY",
    "new_signal": "HOLD"
  },
  {
    "time": "2026-05-28T19:22:21.349898",
    "pair": "INJ-USD",
    "old_signal": "BUY",
    "new_signal": "HOLD"
  },
  {
    "time": "2026-05-28T19:22:21.349901",
    "pair": "FET-USD",
    "old_signal": "BUY",
    "new_signal": "HOLD"
  },
  {
    "time": "2026-05-28T19:22:21.349906",
    "pair": "ADA-USD",
    "old_signal": "BUY",
    "new_signal": "HOLD"
  },
  {
    "time": "2026-05-28T19:37:30.236767",
    "pair": "ICP-USD",
    "old_signal": "HOLD",
    "new_signal": "BUY"
  },
  {
    "time": "2026-05-28T19:37:30.236776",
    "pair": "INJ-USD",
    "old_signal": "HOLD",
    "new_signal": "BUY"
  },
  {
    "time": "2026-05-28T19:37:30.236780",
    "pair": "FET-USD",
    "old_signal": "HOLD",
    "new_signal": "BUY"
  },
  {
    "time": "2026-05-28T19:37:30.236784",
    "pair": "ADA-USD",
    "old_signal": "HOLD",
    "new_signal": "BUY"
  },
  {
    "time": "2026-05-28T19:37:30.236788",
    "pair": "SUI-USD",
    "old_signal": "HOLD",
    "new_signal": "BUY"
  },
  {
    "time": "2026-05-28T19:37:30.236798",
    "pair": "SEI-USD",
    "old_signal": "BUY",
    "new_signal": "HOLD"
  },
  {
    "time": "2026-05-28T19:52:38.461655",
    "pair": "DOT-USD",
    "old_signal": "HOLD",
    "new_signal": "BUY"
  },
  {
    "time": "2026-05-28T19:52:38.461664",
    "pair": "DOGE-USD",
    "old_signal": "HOLD",
    "new_signal": "BUY"
  },
  {
    "time": "2026-05-28T19:52:38.461668",
    "pair": "UNI-USD",
    "old_signal": "HOLD",
    "new_signal": "BUY"
  },
  {
    "time": "2026-05-28T19:52:38.461672",
    "pair": "APT-USD",
    "old_signal": "HOLD",
    "new_signal": "BUY"
  },
  {
    "time": "2026-05-28T19:52:38.461676",
    "pair": "ICP-USD",
    "old_signal": "BUY",
    "new_signal": "HOLD"
  },
  {
    "time": "2026-05-28T19:52:38.461680",
    "pair": "SHIB-USD",
    "old_signal": "BUY",
    "new_signal": "HOLD"
  },
  {
    "time": "2026-05-28T19:52:38.461684",
    "pair": "ADA-USD",
    "old_signal": "BUY",
    "new_signal": "HOLD"
  },
  {
    "time": "2026-05-28T19:52:38.461689",
    "pair": "SUI-USD",
    "old_signal": "BUY",
    "new_signal": "HOLD"
  },
  {
    "time": "2026-05-28T20:07:46.742098",
    "pair": "MATIC-USD",
    "old_signal": "BUY",
    "new_signal": "HOLD"
  },
  {
    "time": "2026-05-28T20:07:46.742106",
    "pair": "INJ-USD",
    "old_signal": "BUY",
    "new_signal": "HOLD"
  },
  {
    "time": "2026-05-28T20:07:46.742112",
    "pair": "FET-USD",
    "old_signal": "BUY",
    "new_signal": "HOLD"
  },
  {
    "time": "2026-05-28T20:07:46.742118",
    "pair": "UNI-USD",
    "old_signal": "BUY",
    "new_signal": "HOLD"
  },
  {
    "time": "2026-05-28T20:07:46.742124",
    "pair": "APT-USD",
    "old_signal": "BUY",
    "new_signal": "HOLD"
  },
  {
    "time": "2026-05-28T20:07:46.742130",
    "pair": "DOT-USD",
    "old_signal": "BUY",
    "new_signal": "HOLD"
  },
  {
    "time": "2026-05-28T20:07:46.742135",
    "pair": "DOGE-USD",
    "old_signal": "BUY",
    "new_signal": "HOLD"
  },
  {
    "time": "2026-05-28T20:22:55.409943",
    "pair": "AAVE-USD",
    "old_signal": "HOLD",
    "new_signal": "STRONG_BUY"
  },
  {
    "time": "2026-05-28T20:22:55.409954",
    "pair": "NEAR-USD",
    "old_signal": "HOLD",
    "new_signal": "BUY"
  },
  {
    "time": "2026-05-28T20:22:55.409958",
    "pair": "MATIC-USD",
    "old_signal": "HOLD",
    "new_signal": "BUY"
  },
  {
    "time": "2026-05-28T20:22:55.409962",
    "pair": "BTC-USD",
    "old_signal": "HOLD",
    "new_signal": "BUY"
  },
  {
    "time": "2026-05-28T20:22:55.409965",
    "pair": "AVAX-USD",
    "old_signal": "HOLD",
    "new_signal": "BUY"
  },
  {
    "time": "2026-05-28T20:38:05.202025",
    "pair": "INJ-USD",
    "old_signal": "HOLD",
    "new_signal": "BUY"
  },
  {
    "time": "2026-05-28T20:38:05.202035",
    "pair": "FET-USD",
    "old_signal": "HOLD",
    "new_signal": "BUY"
  },
  {
    "time": "2026-05-28T20:38:05.202039",
    "pair": "XRP-USD",
    "old_signal": "HOLD",
    "new_signal": "BUY"
  },
  {
    "time": "2026-05-28T20:38:05.202043",
    "pair": "SHIB-USD",
    "old_signal": "HOLD",
    "new_signal": "BUY"
  },
  {
    "time": "2026-05-28T20:38:05.202047",
    "pair": "AAVE-USD",
    "old_signal": "STRONG_BUY",
    "new_signal": "BUY"
  },
  {
    "time": "2026-05-28T20:53:13.238962",
    "pair": "INJ-USD",
    "old_signal": "BUY",
    "new_signal": "STRONG_BUY"
  },
  {
    "time": "2026-05-28T20:53:13.238972",
    "pair": "ICP-USD",
    "old_signal": "HOLD",
    "new_signal": "STRONG_BUY"
  },
  {
    "time": "2026-05-28T20:53:13.238976",
    "pair": "APT-USD",
    "old_signal": "HOLD",
    "new_signal": "STRONG_BUY"
  },
  {
    "time": "2026-05-28T20:53:13.238980",
    "pair": "ARB-USD",
    "old_signal": "HOLD",
    "new_signal": "STRONG_BUY"
  },
  {
    "time": "2026-05-28T20:53:13.238985",
    "pair": "HBAR-USD",
    "old_signal": "HOLD",
    "new_signal": "BUY"
  },
  {
    "time": "2026-05-28T20:53:13.238990",
    "pair": "DOT-USD",
    "old_signal": "HOLD",
    "new_signal": "BUY"
  },
  {
    "time": "2026-05-28T20:53:13.239000",
    "pair": "AAVE-USD",
    "old_signal": "BUY",
    "new_signal": "HOLD"
  },
  {
    "time": "2026-05-28T21:08:21.772223",
    "pair": "DOGE-USD",
    "old_signal": "HOLD",
    "new_signal": "BUY"
  },
  {
    "time": "2026-05-28T21:08:21.772236",
    "pair": "AAVE-USD",
    "old_signal": "HOLD",
    "new_signal": "BUY"
  },
  {
    "time": "2026-05-28T21:08:21.772241",
    "pair": "BTC-USD",
    "old_signal": "BUY",
    "new_signal": "HOLD"
  },
  {
    "time": "2026-05-28T21:08:21.772245",
    "pair": "NEAR-USD",
    "old_signal": "BUY",
    "new_signal": "HOLD"
  },
  {
    "time": "2026-05-28T21:08:21.772249",
    "pair": "ARB-USD",
    "old_signal": "STRONG_BUY",
    "new_signal": "HOLD"
  },
  {
    "time": "2026-05-28T21:08:21.772253",
    "pair": "INJ-USD",
    "old_signal": "STRONG_BUY",
    "new_signal": "HOLD"
  },
  {
    "time": "2026-05-28T21:08:21.772257",
    "pair": "FET-USD",
    "old_signal": "BUY",
    "new_signal": "HOLD"
  },
  {
    "time": "2026-05-28T21:08:21.772262",
    "pair": "HBAR-USD",
    "old_signal": "BUY",
    "new_signal": "HOLD"
  },
  {
    "time": "2026-05-28T21:08:21.772266",
    "pair": "DOT-USD",
    "old_signal": "BUY",
    "new_signal": "HOLD"
  },
  {
    "time": "2026-05-28T21:08:21.772271",
    "pair": "SHIB-USD",
    "old_signal": "BUY",
    "new_signal": "HOLD"
  },
  {
    "time": "2026-05-28T21:08:21.772277",
    "pair": "APT-USD",
    "old_signal": "STRONG_BUY",
    "new_signal": "HOLD"
  },
  {
    "time": "2026-05-28T21:08:21.772283",
    "pair": "ICP-USD",
    "old_signal": "STRONG_BUY",
    "new_signal": "HOLD"
  },
  {
    "time": "2026-05-28T21:08:21.772287",
    "pair": "XRP-USD",
    "old_signal": "BUY",
    "new_signal": "HOLD"
  },
  {
    "time": "2026-05-28T21:08:21.772291",
    "pair": "AVAX-USD",
    "old_signal": "BUY",
    "new_signal": "HOLD"
  }
]